Workbook
Name _Act_M: #REF!
Name _Act_Y: #REF!
Name _AL_Setup: #REF!
Name _Books: #REF!
Name _H: [1]Info!$C$12
Name _Import: #REF!
Name _Import_BS: #REF!
Name _Import_KPI: #REF!
Name _Import_Sales_Books: #REF!
Name _Import_Sales_NonBooks: #REF!
Name _Lines: #REF!
Name _List_Rep: #REF!
Name _Nb: N(#REF!)+1
Name _P_Act_M: #REF!
Name _P_Comp: #REF!
Name _P_Curr_R: #REF!
Name _P_FM: #REF!
Name _P_FX_EUR: #REF!
Name _P_FX_Rep: #REF!
Name _P_FY: #REF!
Name _P_LY_Closed: #REF!
Name _P_U: #REF!
Name _P_U_R: #REF!
Name _Products: #REF!
Name _R: #REF!
Name _R_III: #REF!
Name _R_Rows: #REF!
Name _Rep: #REF!
Name _S_AK: #REF!
Name _S_AK_II: #REF!
Name _S_BS: #REF!
Name _S_Dist: #REF!
Name _S_H: #REF!
Name _S_Months: #REF!
Name _S_Months_I: #REF!
Name _S_Months_Select: #REF!
Name _S_Periods_I: #REF!
Name _S_Rep_Lines: #REF!
Name _S_Types_I: #REF!
Name _S_Ucel: #REF!
Name _S_Ucel_Al: #REF!
Name _S_Units: #REF!
Name _S_Units_I: #REF!
Name _S_Years_I: #REF!
Name _Sales_Ch: #REF!
Name _Sales_Ch_M: #REF!
Name _Setup: #REF!
Name _U: #REF!
Name dwasdsa: #REF!
Name EUR_CZK: #REF!
Name IQ_CH: 110000
Name IQ_CQ: 5000
Name IQ_CY: 10000
Name IQ_DAILY: 500000
Name IQ_FH: 100000
Name IQ_FQ: 500
Name IQ_FY: 1000
Name IQ_LTM: 2000
Name IQ_MONTH: 15000
Name IQ_NTM: 6000

Sheet __snloffice
A1: 允䅁䉁䄸䅁䍁䅁䅁䅁摁䅁䅁杋䅁䍁䅧兓畂䡁䅙兙獂䝁䅫䅚杁䕁䅫䅚求䝁䄴䅤灂䝁䅙兡求䡁䅉克䅁䉁䄴䅁佁䅁䅁睉䙂䙁䅉杕偂䙁䅉䅁扁䅁䅁杌䅁䍁䅧兓畂䡁䅙兙獂䝁䅫䅚杁䕁䅙睢祂䝁䄰兤獂䝁䅅䅉佂䝁䅅兢求䍁䅫䅁坁䅁䅁杋䅁䍁䅍兓佂䙁䅙兑䵂䕁䅫䅒杁䕁䄰兒啂䙁䅉兓䑂䍁䅁杔䉂䕁䄰兒䅁䉁䅅䅁敁䅁䅁兓剂䙁䄸䅉䑂䕁䅷睔呂䕁䅕䅕卂䕁䅫睑䙂䅁䅁兆䅁䉁䅑䅁硁䑁䅑兌䝂䝁䅕杙瑁䑁䅉杍䅁䉁䅑䅁允䅁䅁䅊兂䕁䅷杔䙂䙁䅕杕䅁䉁䅉䅁坁䅁䅁免ぁ䍁䄴䅍祁䍁䄴杍睁䑁䅉杍䅁䅁䄸䅁䥁䅁䅁兒噂䙁䅉䅁䕁䅁䅁䅅䅁䕁䅙兕硁䑁䅉䅍祁䑁䅉䅁䱁䅁䅁䅅䅁䕁䅙兕硁䑁䅉䅍祁䑁䅍䅁慁䅁䅁䅅䅁䕁䅙兕祁䑁䅉䅍祁䑁䅉䅁乁䅁䅁䅅䅁䕁䅙兕祁䑁䅉䅍祁䑁䅍䅁捁䅁䅁䅅䅁䕁䅙兕穁䑁䅉䅍祁䑁䅉䅁䝁䅁䅁䅅䅁䕁䅙兕ぁ䑁䅉䅍祁䑁䅉䅁奁䅁䅁杄䅁䕁䅙兗祁䑁䅁杍祁䅁䅁睁䅁䅁䄴䅁䝂䙁䅫杍睁䑁䅉睍䅁䉁䅫䅁歁䅁䅁兓剂䙁䄸䅉䵂䕁䅅睕啂䙁䅍兑䵂䕁䅕䅕卂䕁䅫睑䙂䅁䅁睆䅁䉁䅷䅁䩂䙁䅅睘䙂䕁䅉兓啂䕁䅑兑時䕁䅕睕啂䅁䅁元䅁䉁䅯䅁䩂䙁䅅睘䑂䕁䅅䅕䙂䙁䅧睘䙂䙁䅍䅖䅁䅁䅉䅁捁䅁䅁兓剂䙁䄸睑䵂䕁䄸睕䙂䙁䅁杕䩂䕁䅍兒䅁䅁䄴䅁潁䅁䅁兓剂䙁䄸睒卂䕁䄸睕呂䙁䄸兔䉂䙁䅉睒䩂䕁䄴睘䙂䙁䅍䅖䅁䅁䅣䅁楁䅁䅁兓剂䙁䄸䅔䉂䙁䅍䅖呂䕁䅅䅔䙂䙁䅁杕䩂䕁䅍兒䅁䅁䅅䅁慁䅁䅁兓剂䙁䄸兔䉂䙁䅉睓䙂䙁䅑睑䉂䙁䅁䅁䭁䅁䅁䅉䅁䕁䅫兕時䕁䄴兒啂䙁䄸䅒䙂䕁䅉䅖時䕁䅕睕啂䅁䅁䅄䅁䉁䄴䅁䩂䙁䅅睘卂䕁䅕杖䙂䕁䄴兖䙂䙁䄸兒呂䙁䅑䅁䙁䅁䅁杄䅁䕁䅫兕時䙁䅑兒坂䅁䅁䅅䅁䅁䅙䅁佂䕁䅅䅁䥁䅁䅁杉䅁䙁䅍䅕時䕁䅷兑呂䙁䅑睕䉂䕁䅷兒兂䙁䅉兓䑂䕁䅕䅁呁䅁䅁䅅䅁䙁䅣睕䙂䑁䅯兑䵂䕁䅕䅁䅁䅁䅁䅁䅁䅁㴽

Sheet EMG
W3: =TODAY() -> 46172
C5: Company: | D5: Euromedia Group | G5: Ownership: | I5: 1
C6: Year: | D6: 2026 | G6: FY: | I6: =IF(COUNTIF(_xlfn.ANCHORARRAY(K53),$D$8)>0,$D$6,$D$6+1) -> 2026
C7: Month: | D7: February
C8: FY month numnber | D8: =VLOOKUP(D7,C53:E64,3,FALSE) -> 2
C10: Financial Indicators | G10: Totals | K10: Year to date development | R10: Month to date development
G11: Actual | H11: Actual | I11: Budget | K11: Actual | L11: Budget | M11: Act vs. | O11: Actual | P11: Act vs. | R11: Actual | S11: Budget | T11: Act vs. | V11: Act LY | W11: Act vs.
G12: =IF(D8<=12,I6-2002,I6-2001) -> 24 | H12: =G12+1 -> 25 | I12: =H12+1 -> 26 | K12: =I12 -> 26 | L12: =K12 -> 26 | O12: =L12-1 -> 25 | R12: =I12 -> 26 | S12: =R12 -> 26 | V12: =S12-1 -> 25
C13: CZK mil. (unless otherwise stated) | G13: ="FY"&G12 -> FY24 | H13: ="FY"&H12 -> FY25 | I13: ="FY"&I12 -> FY26 | K13: ="YTD FY"&K12 -> YTD FY26 | L13: ="YTD FY"&L12 -> YTD FY26 | M13: Bud | O13: ="YTD FY"&O12 -> YTD FY25 | P13: LY | R13: =LEFT($D$7,3) -> Feb | S13: =LEFT($D$7,3) -> Feb | T13: Bud | V13: =LEFT($D$7,3) -> Feb | W13: LY
C15: Retail | G15: =IFERROR(SUMIF(EMG_act!$C$2:$CI$2,G$12,EMG_act!$C12:$CI12),"-") -> 0 | H15: =IFERROR(SUMIF(EMG_act!$C$2:$CI$2,H$12,EMG_act!$C12:$CI12),"-") -> 0 | I15: =IFERROR(SUMIF(EMG_bud!$C$2:$CI$2,I$12,EMG_bud!#REF!),"-") -> - | K15: =IFERROR(SUMIFS(EMG_act!$C12:$CC12,EMG_act!$C$2:$CC$2,K$12,EMG_act!$C$3:$CC$3,"<="&$D$8),"-") -> 0 | L15: =IFERROR(SUMIFS(EMG_bud!#REF!,EMG_bud!$C$2:$CC$2,L$12,EMG_bud!$C$3:$CC$3,"<="&$D$8),"-") -> - | M15: =IF(OR(AND(K15<0,L15<0),AND(K15>0,L15<0)),-IFERROR(K15/L15-1,"-"),IFERROR(K15/L15-1,"-")) -> - | O15: =IFERROR(SUMIFS(EMG_act!$C12:$CC12,EMG_act!$C$2:$CC$2,O$12,EMG_act!$C$3:$CC$3,"<="&$D$8),"-") -> 0 | P15: =IF(OR(AND(K15<0,O15<0),AND(K15>0,O15<0)),-IFERROR(K15/O15-1,"-"),IFERROR(K15/O15-1,"-")) -> - | R15: =IFERROR(SUMIFS(EMG_act!$C12:$CC12,EMG_act!$C$2:$CC$2,R$12,EMG_act!$C$3:$CC$3,$D$8),"-") -> 0 | S15: =IFERROR(SUMIFS(EMG_bud!#REF!,EMG_bud!$C$2:$CC$2,S$12,EMG_bud!$C$3:$CC$3,$D$8),"-") -> - | T15: =IF(OR(AND(R15<0,S15<0),AND(R15>0,S15<0)),-IFERROR(R15/S15-1,"-"),IFERROR(R15/S15-1,"-")) -> - | V15: =IFERROR(SUMIFS(EMG_act!$C12:$CC12,EMG_act!$C$2:$CC$2,V$12,EMG_act!$C$3:$CC$3,$D$8),"-") -> 0 | W15: =IF(OR(AND(R15<0,V15<0),AND(R15>0,V15<0)),-IFERROR(R15/V15-1,"-"),IFERROR(R15/V15-1,"-")) -> -
C16: Distribution | G16: =IFERROR(SUMIF(EMG_act!$C$2:$CI$2,G$12,EMG_act!$C13:$CI13),"-") -> 0 | H16: =IFERROR(SUMIF(EMG_act!$C$2:$CI$2,H$12,EMG_act!$C13:$CI13),"-") -> 0 | I16: =IFERROR(SUMIF(EMG_bud!$C$2:$CI$2,I$12,EMG_bud!#REF!),"-") -> - | K16: =IFERROR(SUMIFS(EMG_act!$C13:$CC13,EMG_act!$C$2:$CC$2,K$12,EMG_act!$C$3:$CC$3,"<="&$D$8),"-") -> 0 | L16: =IFERROR(SUMIFS(EMG_bud!#REF!,EMG_bud!$C$2:$CC$2,L$12,EMG_bud!$C$3:$CC$3,"<="&$D$8),"-") -> - | M16: =IF(OR(AND(K16<0,L16<0),AND(K16>0,L16<0)),-IFERROR(K16/L16-1,"-"),IFERROR(K16/L16-1,"-")) -> - | O16: =IFERROR(SUMIFS(EMG_act!$C13:$CC13,EMG_act!$C$2:$CC$2,O$12,EMG_act!$C$3:$CC$3,"<="&$D$8),"-") -> 0 | P16: =IF(OR(AND(K16<0,O16<0),AND(K16>0,O16<0)),-IFERROR(K16/O16-1,"-"),IFERROR(K16/O16-1,"-")) -> - | R16: =IFERROR(SUMIFS(EMG_act!$C13:$CC13,EMG_act!$C$2:$CC$2,R$12,EMG_act!$C$3:$CC$3,$D$8),"-") -> 0 | S16: =IFERROR(SUMIFS(EMG_bud!#REF!,EMG_bud!$C$2:$CC$2,S$12,EMG_bud!$C$3:$CC$3,$D$8),"-") -> - | T16: =IF(OR(AND(R16<0,S16<0),AND(R16>0,S16<0)),-IFERROR(R16/S16-1,"-"),IFERROR(R16/S16-1,"-")) -> - | V16: =IFERROR(SUMIFS(EMG_act!$C13:$CC13,EMG_act!$C$2:$CC$2,V$12,EMG_act!$C$3:$CC$3,$D$8),"-") -> 0 | W16: =IF(OR(AND(R16<0,V16<0),AND(R16>0,V16<0)),-IFERROR(R16/V16-1,"-"),IFERROR(R16/V16-1,"-")) -> -
C17: Publishing | G17: =IFERROR(SUMIF(EMG_act!$C$2:$CI$2,G$12,EMG_act!$C14:$CI14),"-") -> 0 | H17: =IFERROR(SUMIF(EMG_act!$C$2:$CI$2,H$12,EMG_act!$C14:$CI14),"-") -> 0 | I17: =IFERROR(SUMIF(EMG_bud!$C$2:$CI$2,I$12,EMG_bud!#REF!),"-") -> - | K17: =IFERROR(SUMIFS(EMG_act!$C14:$CC14,EMG_act!$C$2:$CC$2,K$12,EMG_act!$C$3:$CC$3,"<="&$D$8),"-") -> 0 | L17: =IFERROR(SUMIFS(EMG_bud!#REF!,EMG_bud!$C$2:$CC$2,L$12,EMG_bud!$C$3:$CC$3,"<="&$D$8),"-") -> - | M17: =IF(OR(AND(K17<0,L17<0),AND(K17>0,L17<0)),-IFERROR(K17/L17-1,"-"),IFERROR(K17/L17-1,"-")) -> - | O17: =IFERROR(SUMIFS(EMG_act!$C14:$CC14,EMG_act!$C$2:$CC$2,O$12,EMG_act!$C$3:$CC$3,"<="&$D$8),"-") -> 0 | P17: =IF(OR(AND(K17<0,O17<0),AND(K17>0,O17<0)),-IFERROR(K17/O17-1,"-"),IFERROR(K17/O17-1,"-")) -> - | R17: =IFERROR(SUMIFS(EMG_act!$C14:$CC14,EMG_act!$C$2:$CC$2,R$12,EMG_act!$C$3:$CC$3,$D$8),"-") -> 0 | S17: =IFERROR(SUMIFS(EMG_bud!#REF!,EMG_bud!$C$2:$CC$2,S$12,EMG_bud!$C$3:$CC$3,$D$8),"-") -> - | T17: =IF(OR(AND(R17<0,S17<0),AND(R17>0,S17<0)),-IFERROR(R17/S17-1,"-"),IFERROR(R17/S17-1,"-")) -> - | V17: =IFERROR(SUMIFS(EMG_act!$C14:$CC14,EMG_act!$C$2:$CC$2,V$12,EMG_act!$C$3:$CC$3,$D$8),"-") -> 0 | W17: =IF(OR(AND(R17<0,V17<0),AND(R17>0,V17<0)),-IFERROR(R17/V17-1,"-"),IFERROR(R17/V17-1,"-")) -> -
C18: Elimination | G18: =IFERROR(SUMIF(EMG_act!$C$2:$CI$2,G$12,EMG_act!$C15:$CI15),"-") -> 0 | H18: =IFERROR(SUMIF(EMG_act!$C$2:$CI$2,H$12,EMG_act!$C15:$CI15),"-") -> 0 | I18: =IFERROR(SUMIF(EMG_bud!$C$2:$CI$2,I$12,EMG_bud!#REF!),"-") -> - | K18: =IFERROR(SUMIFS(EMG_act!$C15:$CC15,EMG_act!$C$2:$CC$2,K$12,EMG_act!$C$3:$CC$3,"<="&$D$8),"-") -> 0 | L18: =IFERROR(SUMIFS(EMG_bud!#REF!,EMG_bud!$C$2:$CC$2,L$12,EMG_bud!$C$3:$CC$3,"<="&$D$8),"-") -> - | M18: =IF(OR(AND(K18<0,L18<0),AND(K18>0,L18<0)),-IFERROR(K18/L18-1,"-"),IFERROR(K18/L18-1,"-")) -> - | O18: =IFERROR(SUMIFS(EMG_act!$C15:$CC15,EMG_act!$C$2:$CC$2,O$12,EMG_act!$C$3:$CC$3,"<="&$D$8),"-") -> 0 | P18: =IF(OR(AND(K18<0,O18<0),AND(K18>0,O18<0)),-IFERROR(K18/O18-1,"-"),IFERROR(K18/O18-1,"-")) -> - | R18: =IFERROR(SUMIFS(EMG_act!$C15:$CC15,EMG_act!$C$2:$CC$2,R$12,EMG_act!$C$3:$CC$3,$D$8),"-") -> 0 | S18: =IFERROR(SUMIFS(EMG_bud!#REF!,EMG_bud!$C$2:$CC$2,S$12,EMG_bud!$C$3:$CC$3,$D$8),"-") -> - | T18: =IF(OR(AND(R18<0,S18<0),AND(R18>0,S18<0)),-IFERROR(R18/S18-1,"-"),IFERROR(R18/S18-1,"-")) -> - | V18: =IFERROR(SUMIFS(EMG_act!$C15:$CC15,EMG_act!$C$2:$CC$2,V$12,EMG_act!$C$3:$CC$3,$D$8),"-") -> 0 | W18: =IF(OR(AND(R18<0,V18<0),AND(R18>0,V18<0)),-IFERROR(R18/V18-1,"-"),IFERROR(R18/V18-1,"-")) -> -
C19: Consolidated Revenues | G19: =IFERROR(SUMIF(EMG_act!$C$2:$CI$2,G$12,EMG_act!$C16:$CI16),"-") -> 1058 | H19: =IFERROR(SUMIF(EMG_act!$C$2:$CI$2,H$12,EMG_act!$C16:$CI16),"-") -> 1790 | I19: =IFERROR(SUMIF(EMG_bud!$C$2:$CI$2,I$12,EMG_bud!$C16:$CI16),"-") -> 3703.6121 | K19: =IFERROR(SUMIFS(EMG_act!$C16:$CI16,EMG_act!$C$2:$CI$2,K$12,EMG_act!$C$3:$CI$3,"<="&$D$8),"-") -> 98 | L19: =IFERROR(SUMIFS(EMG_bud!$C16:$CI16,EMG_bud!$C$2:$CI$2,L$12,EMG_bud!$C$3:$CI$3,"<="&$D$8),"-") -> 98 | M19: =IF(OR(AND(K19<0,L19<0),AND(K19>0,L19<0)),-IFERROR(K19/L19-1,"-"),IFERROR(K19/L19-1,"-")) -> 0 | O19: =IFERROR(SUMIFS(EMG_act!$C16:$CI16,EMG_act!$C$2:$CI$2,O$12,EMG_act!$C$3:$CI$3,"<="&$D$8),"-") -> 259 | P19: =IF(OR(AND(K19<0,O19<0),AND(K19>0,O19<0)),-IFERROR(K19/O19-1,"-"),IFERROR(K19/O19-1,"-")) -> -0.62162162 | R19: =IFERROR(SUMIFS(EMG_act!$C16:$CI16,EMG_act!$C$2:$CI$2,R$12,EMG_act!$C$3:$CI$3,$D$8),"-") -> 86 | S19: =IFERROR(SUMIFS(EMG_bud!$C16:$CI16,EMG_bud!$C$2:$CI$2,S$12,EMG_bud!$C$3:$CI$3,$D$8),"-") -> 86 | T19: =IF(OR(AND(R19<0,S19<0),AND(R19>0,S19<0)),-IFERROR(R19/S19-1,"-"),IFERROR(R19/S19-1,"-")) -> 0 | V19: =IFERROR(SUMIFS(EMG_act!$C16:$CI16,EMG_act!$C$2:$CI$2,V$12,EMG_act!$C$3:$CI$3,$D$8),"-") -> 74 | W19: =IF(OR(AND(R19<0,V19<0),AND(R19>0,V19<0)),-IFERROR(R19/V19-1,"-"),IFERROR(R19/V19-1,"-")) -> 0.16216216
C20: Gross Margin | G20: =IFERROR(SUMIF(EMG_act!$C$2:$CI$2,G$12,EMG_act!$C17:$CI17),"-") -> 533 | H20: =IFERROR(SUMIF(EMG_act!$C$2:$CI$2,H$12,EMG_act!$C17:$CI17),"-") -> 804 | I20: =IFERROR(SUMIF(EMG_bud!$C$2:$CI$2,I$12,EMG_bud!$C17:$CI17),"-") -> 1454.9149 | K20: =IFERROR(SUMIFS(EMG_act!$C17:$CI17,EMG_act!$C$2:$CI$2,K$12,EMG_act!$C$3:$CI$3,"<="&$D$8),"-") -> 62 | L20: =IFERROR(SUMIFS(EMG_bud!$C17:$CI17,EMG_bud!$C$2:$CI$2,L$12,EMG_bud!$C$3:$CI$3,"<="&$D$8),"-") -> 62 | M20: =IF(OR(AND(K20<0,L20<0),AND(K20>0,L20<0)),-IFERROR(K20/L20-1,"-"),IFERROR(K20/L20-1,"-")) -> 0 | O20: =IFERROR(SUMIFS(EMG_act!$C17:$CI17,EMG_act!$C$2:$CI$2,O$12,EMG_act!$C$3:$CI$3,"<="&$D$8),"-") -> 171 | P20: =IF(OR(AND(K20<0,O20<0),AND(K20>0,O20<0)),-IFERROR(K20/O20-1,"-"),IFERROR(K20/O20-1,"-")) -> -0.6374269 | R20: =IFERROR(SUMIFS(EMG_act!$C17:$CI17,EMG_act!$C$2:$CI$2,R$12,EMG_act!$C$3:$CI$3,$D$8),"-") -> 17 | S20: =IFERROR(SUMIFS(EMG_bud!$C17:$CI17,EMG_bud!$C$2:$CI$2,S$12,EMG_bud!$C$3:$CI$3,$D$8),"-") -> 17 | T20: =IF(OR(AND(R20<0,S20<0),AND(R20>0,S20<0)),-IFERROR(R20/S20-1,"-"),IFERROR(R20/S20-1,"-")) -> 0 | V20: =IFERROR(SUMIFS(EMG_act!$C17:$CI17,EMG_act!$C$2:$CI$2,V$12,EMG_act!$C$3:$CI$3,$D$8),"-") -> 75 | W20: =IF(OR(AND(R20<0,V20<0),AND(R20>0,V20<0)),-IFERROR(R20/V20-1,"-"),IFERROR(R20/V20-1,"-")) -> -0.77333333
C21: % of Revenues | G21: =IFERROR(G20/G$19,"-") -> 0.50378072 | H21: =IFERROR(H20/H$19,"-") -> 0.44916201 | I21: =IFERROR(I20/I$19,"-") -> 0.39283673 | K21: =IFERROR(K20/K$19,"-") -> 0.63265306 | L21: =IFERROR(L20/L$19,"-") -> 0.63265306 | O21: =IFERROR(O20/O$19,"-") -> 0.66023166 | R21: =IFERROR(R20/R$19,"-") -> 0.19767442 | S21: =IFERROR(S20/S$19,"-") -> 0.19767442 | V21: =IFERROR(V20/V$19,"-") -> 1.0135135
C22: Adjusted EBITDA | G22: =IFERROR(SUMIF(EMG_act!$C$2:$CI$2,G$12,EMG_act!$C29:$CI29),"-") -> 307.57287 | H22: =IFERROR(SUMIF(EMG_act!$C$2:$CI$2,H$12,EMG_act!$C29:$CI29),"-") -> 325.92963 | I22: =IFERROR(SUMIF(EMG_bud!$C$2:$CI$2,I$12,EMG_bud!$C29:$CI29),"-") -> 456.20979 | K22: =IFERROR(SUMIFS(EMG_act!$C29:$CI29,EMG_act!$C$2:$CI$2,K$12,EMG_act!$C$3:$CI$3,"<="&$D$8),"-") -> -1.476238 | L22: =IFERROR(SUMIFS(EMG_bud!$C29:$CI29,EMG_bud!$C$2:$CI$2,L$12,EMG_bud!$C$3:$CI$3,"<="&$D$8),"-") -> 60 | M22: =IF(OR(AND(K22<0,L22<0),AND(K22>0,L22<0)),-IFERROR(K22/L22-1,"-"),IFERROR(K22/L22-1,"-")) -> -1.024604 | O22: =IFERROR(SUMIFS(EMG_act!$C29:$CI29,EMG_act!$C$2:$CI$2,O$12,EMG_act!$C$3:$CI$3,"<="&$D$8),"-") -> 40.144338 | P22: =IF(OR(AND(K22<0,O22<0),AND(K22>0,O22<0)),-IFERROR(K22/O22-1,"-"),IFERROR(K22/O22-1,"-")) -> -1.0367733 | R22: =IFERROR(SUMIFS(EMG_act!$C29:$CI29,EMG_act!$C$2:$CI$2,R$12,EMG_act!$C$3:$CI$3,$D$8),"-") -> -1.8639256 | S22: =IFERROR(SUMIFS(EMG_bud!$C29:$CI29,EMG_bud!$C$2:$CI$2,S$12,EMG_bud!$C$3:$CI$3,$D$8),"-") -> 41 | T22: =IF(OR(AND(R22<0,S22<0),AND(R22>0,S22<0)),-IFERROR(R22/S22-1,"-"),IFERROR(R22/S22-1,"-")) -> -1.0454616 | V22: =IFERROR(SUMIFS(EMG_act!$C29:$CI29,EMG_act!$C$2:$CI$2,V$12,EMG_act!$C$3:$CI$3,$D$8),"-") -> 3.0284652 | W22: =IF(OR(AND(R22<0,V22<0),AND(R22>0,V22<0)),-IFERROR(R22/V22-1,"-"),IFERROR(R22/V22-1,"-")) -> -1.6154687
C23: % of Revenues | G23: =IFERROR(G22/G$19,"-") -> 0.2907116 | H23: =IFERROR(H22/H$19,"-") -> 0.18208359 | I23: =IFERROR(I22/I$19,"-") -> 0.12317969 | K23: =IFERROR(K22/K$19,"-") -> -0.015063653 | L23: =IFERROR(L22/L$19,"-") -> 0.6122449 | O23: =IFERROR(O22/O$19,"-") -> 0.15499744 | R23: =IFERROR(R22/R$19,"-") -> -0.021673553 | S23: =IFERROR(S22/S$19,"-") -> 0.47674419 | V23: =IFERROR(V22/V$19,"-") -> 0.040925206
C24: CAPEX | G24: =IFERROR(SUMIF(EMG_act!$C$2:$CI$2,G$12,EMG_act!$C21:$CI21),"-") -> 130 | H24: =IFERROR(SUMIF(EMG_act!$C$2:$CI$2,H$12,EMG_act!$C21:$CI21),"-") -> 108 | I24: =IFERROR(SUMIF(EMG_bud!$C$2:$CI$2,I$12,EMG_bud!$C21:$CI21),"-") -> -105.25265 | K24: =IFERROR(SUMIFS(EMG_act!$C21:$CI21,EMG_act!$C$2:$CI$2,K$12,EMG_act!$C$3:$CI$3,"<="&$D$8),"-") -> 19 | L24: =IFERROR(SUMIFS(EMG_bud!$C21:$CI21,EMG_bud!$C$2:$CI$2,L$12,EMG_bud!$C$3:$CI$3,"<="&$D$8),"-") -> 19 | M24: =IF(OR(AND(K24<0,L24<0),AND(K24>0,L24<0)),-IFERROR(K24/L24-1,"-"),IFERROR(K24/L24-1,"-")) -> 0 | O24: =IFERROR(SUMIFS(EMG_act!$C21:$CI21,EMG_act!$C$2:$CI$2,O$12,EMG_act!$C$3:$CI$3,"<="&$D$8),"-") -> 9 | P24: =IF(OR(AND(K24<0,O24<0),AND(K24>0,O24<0)),-IFERROR(K24/O24-1,"-"),IFERROR(K24/O24-1,"-")) -> 1.1111111 | R24: =IFERROR(SUMIFS(EMG_act!$C21:$CI21,EMG_act!$C$2:$CI$2,R$12,EMG_act!$C$3:$CI$3,$D$8),"-") -> 9 | S24: =IFERROR(SUMIFS(EMG_bud!$C21:$CI21,EMG_bud!$C$2:$CI$2,S$12,EMG_bud!$C$3:$CI$3,$D$8),"-") -> 9 | T24: =IF(OR(AND(R24<0,S24<0),AND(R24>0,S24<0)),-IFERROR(R24/S24-1,"-"),IFERROR(R24/S24-1,"-")) -> 0 | V24: =IFERROR(SUMIFS(EMG_act!$C21:$CI21,EMG_act!$C$2:$CI$2,V$12,EMG_act!$C$3:$CI$3,$D$8),"-") -> 3 | W24: =IF(OR(AND(R24<0,V24<0),AND(R24>0,V24<0)),-IFERROR(R24/V24-1,"-"),IFERROR(R24/V24-1,"-")) -> 2
C25: OpCF (EBITDA less Capex) | G25: =G22-G24 -> 177.57287 | H25: =H22-H24 -> 217.92963 | I25: =I22-I24 -> 561.46245 | K25: =K22-K24 -> -20.476238 | L25: =L22-L24 -> 41 | M25: =IF(OR(AND(K25<0,L25<0),AND(K25>0,L25<0)),-IFERROR(K25/L25-1,"-"),IFERROR(K25/L25-1,"-")) -> -1.4994204 | O25: =O22-O24 -> 31.144338 | P25: =IF(OR(AND(K25<0,O25<0),AND(K25>0,O25<0)),-IFERROR(K25/O25-1,"-"),IFERROR(K25/O25-1,"-")) -> -1.6574626 | R25: =R22-R24 -> -10.863926 | S25: =S22-S24 -> 32 | T25: =IF(OR(AND(R25<0,S25<0),AND(R25>0,S25<0)),-IFERROR(R25/S25-1,"-"),IFERROR(R25/S25-1,"-")) -> -1.3394977 | V25: =V22-V24 -> 0.02846522 | W25: =IF(OR(AND(R25<0,V25<0),AND(R25>0,V25<0)),-IFERROR(R25/V25-1,"-"),IFERROR(R25/V25-1,"-")) -> -382.65613
C26: Debt | G26: =IFERROR(SUMIFS(EMG_act!$C23:$CI23,EMG_act!$C$2:$CI$2,G$12,EMG_act!$C$3:$CI$3,12),"-") -> 972 | H26: =IFERROR(SUMIFS(EMG_act!$C23:$CI23,EMG_act!$C$2:$CI$2,H$12,EMG_act!$C$3:$CI$3,12),"-") -> 972 | I26: =IFERROR(SUMIFS(EMG_bud!$C23:$CI23,EMG_bud!$C$2:$CI$2,I$12,EMG_bud!$C$3:$CI$3,12),"-") -> 905.96053 | K26: =IFERROR(SUMIFS(EMG_act!$C23:$CI23,EMG_act!$C$2:$CI$2,K$12,EMG_act!$C$3:$CI$3,$D$8),"-") -> 972 | L26: =IFERROR(SUMIFS(EMG_bud!$C23:$CI23,EMG_bud!$C$2:$CI$2,L$12,EMG_bud!$C$3:$CI$3,$D$8),"-") -> 972 | M26: =IF(OR(AND(K26<0,L26<0),AND(K26>0,L26<0)),-IFERROR(K26/L26-1,"-"),IFERROR(K26/L26-1,"-")) -> 0 | O26: =IFERROR(SUMIFS(EMG_act!$C23:$CI23,EMG_act!$C$2:$CI$2,O$12,EMG_act!$C$3:$CI$3,$D$8),"-") -> 972 | P26: =IF(OR(AND(K26<0,O26<0),AND(K26>0,O26<0)),-IFERROR(K26/O26-1,"-"),IFERROR(K26/O26-1,"-")) -> 0 | R26: =IFERROR(SUMIFS(EMG_act!$C23:$CI23,EMG_act!$C$2:$CI$2,R$12,EMG_act!$C$3:$CI$3,$D$8),"-") -> 972 | S26: =IFERROR(SUMIFS(EMG_bud!$C23:$CI23,EMG_bud!$C$2:$CI$2,S$12,EMG_bud!$C$3:$CI$3,$D$8),"-") -> 972 | T26: =IF(OR(AND(R26<0,S26<0),AND(R26>0,S26<0)),-IFERROR(R26/S26-1,"-"),IFERROR(R26/S26-1,"-")) -> 0 | V26: =IFERROR(SUMIFS(EMG_act!$C23:$CI23,EMG_act!$C$2:$CI$2,V$12,EMG_act!$C$3:$CI$3,$D$8),"-") -> 972 | W26: =IF(OR(AND(R26<0,V26<0),AND(R26>0,V26<0)),-IFERROR(R26/V26-1,"-"),IFERROR(R26/V26-1,"-")) -> 0
C27: Cash | G27: =IFERROR(SUMIFS(EMG_act!$C24:$CI24,EMG_act!$C$2:$CI$2,G$12,EMG_act!$C$3:$CI$3,12),"-") -> 15 | H27: =IFERROR(SUMIFS(EMG_act!$C24:$CI24,EMG_act!$C$2:$CI$2,H$12,EMG_act!$C$3:$CI$3,12),"-") -> 13 | I27: =IFERROR(SUMIFS(EMG_bud!$C24:$CI24,EMG_bud!$C$2:$CI$2,I$12,EMG_bud!$C$3:$CI$3,12),"-") -> 64.034262 | K27: =IFERROR(SUMIFS(EMG_act!$C24:$CI24,EMG_act!$C$2:$CI$2,K$12,EMG_act!$C$3:$CI$3,$D$8),"-") -> 79 | L27: =IFERROR(SUMIFS(EMG_bud!$C24:$CI24,EMG_bud!$C$2:$CI$2,L$12,EMG_bud!$C$3:$CI$3,$D$8),"-") -> 79 | M27: =IF(OR(AND(K27<0,L27<0),AND(K27>0,L27<0)),-IFERROR(K27/L27-1,"-"),IFERROR(K27/L27-1,"-")) -> 0 | O27: =IFERROR(SUMIFS(EMG_act!$C24:$CI24,EMG_act!$C$2:$CI$2,O$12,EMG_act!$C$3:$CI$3,$D$8),"-") -> 44 | P27: =IF(OR(AND(K27<0,O27<0),AND(K27>0,O27<0)),-IFERROR(K27/O27-1,"-"),IFERROR(K27/O27-1,"-")) -> 0.79545455 | R27: =IFERROR(SUMIFS(EMG_act!$C24:$CI24,EMG_act!$C$2:$CI$2,R$12,EMG_act!$C$3:$CI$3,$D$8),"-") -> 79 | S27: =IFERROR(SUMIFS(EMG_bud!$C24:$CI24,EMG_bud!$C$2:$CI$2,S$12,EMG_bud!$C$3:$CI$3,$D$8),"-") -> 79 | T27: =IF(OR(AND(R27<0,S27<0),AND(R27>0,S27<0)),-IFERROR(R27/S27-1,"-"),IFERROR(R27/S27-1,"-")) -> 0 | V27: =IFERROR(SUMIFS(EMG_act!$C24:$CI24,EMG_act!$C$2:$CI$2,V$12,EMG_act!$C$3:$CI$3,$D$8),"-") -> 44 | W27: =IF(OR(AND(R27<0,V27<0),AND(R27>0,V27<0)),-IFERROR(R27/V27-1,"-"),IFERROR(R27/V27-1,"-")) -> 0.79545455
C28: Net Debt / LTM EBITDA | G28: {=IFERROR(_xlfn.XLOOKUP(1,(EMG_act!$C$2:$CI$2=G$12)*(EMG_act!$C$3:$CI$3=12),EMG_act!$C$25:$CI$25),"n/a")} -> 3.1114578 | H28: {=IFERROR(_xlfn.XLOOKUP(1,(EMG_act!$C$2:$CI$2=H$12)*(EMG_act!$C$3:$CI$3=12),EMG_act!$C$25:$CI$25),"n/a")} -> 2.9423529 | I28: {=IFERROR(_xlfn.XLOOKUP(1,(EMG_bud!$C$2:$CI$2=I$12)*(EMG_bud!$C$3:$CI$3=12),EMG_bud!$C$25:$CI$25),"n/a")} -> 2.0759068 | K28: {=IFERROR(_xlfn.XLOOKUP(1,(EMG_act!$C$2:$CI$2=K$12)*(EMG_act!$C$3:$CI$3=$D$8),EMG_act!$C$25:$CI$25),"n/a")} -> 3.1409482 | L28: {=IFERROR(_xlfn.XLOOKUP(1,(EMG_bud!$C$2:$CI$2=L$12)*(EMG_bud!$C$3:$CI$3=$D$8),EMG_bud!$C$25:$CI$25),"n/a")} -> 3.1409482 | M28: {=IF(AND(ISNUMBER(K28), ISNUMBER(L28)), _xlfn.IFS( AND(L28 < 0, K28 < 0, K28 > L28), K28 / L28 - 1, AND(L28 < 0, K28 < 0, K28 <= L28), -(K28 / L28 - 1), AND(L28 < 0, K28 > 0), -(K28 / L28 - 1), AND(L28 > 0, K28 > 0), -(K28 / L28 - 1), AND(L28 > 0, K28 < 0), -(K28 / L28 - 1) ), "-" )} -> 0 | O28: {=IFERROR(_xlfn.XLOOKUP(1,(EMG_act!$C$2:$CI$2=O$12)*(EMG_act!$C$3:$CI$3=$D$8),EMG_act!$C$25:$CI$25),"n/a")} -> 2.774826 | P28: {=IF(AND(ISNUMBER(K28), ISNUMBER(O28)), _xlfn.IFS( AND(O28 < 0, K28 < 0, K28 > O28), K28 / O28 - 1, AND(O28 < 0, K28 < 0, K28 <= O28), -(K28 / O28 - 1), AND(O28 < 0, K28 > 0), -(K28 / O28 - 1), AND(O28 > 0, K28 > 0), -(K28 / O28 - 1), AND(O28 > 0, K28 < 0), -(K28 / O28 - 1) ), "-" )} -> -0.13194419 | R28: {=IFERROR(_xlfn.XLOOKUP(1,(EMG_act!$C$2:$CI$2=R$12)*(EMG_act!$C$3:$CI$3=$D$8),EMG_act!$C$25:$CI$25),"n/a")} -> 3.1409482 | S28: {=IFERROR(_xlfn.XLOOKUP(1,(EMG_bud!$C$2:$CI$2=S$12)*(EMG_bud!$C$3:$CI$3=$D$8),EMG_bud!$C$25:$CI$25),"n/a")} -> 3.1409482 | T28: {=IF(AND(ISNUMBER(R28), ISNUMBER(S28)), _xlfn.IFS( AND(S28 < 0, R28 < 0, R28 > S28), R28 / S28 - 1, AND(S28 < 0, R28 < 0, R28 <= S28), -(R28 / S28 - 1), AND(S28 < 0, R28 > 0), -(R28 / S28 - 1), AND(S28 > 0, R28 > 0), -(R28 / S28 - 1), AND(S28 > 0, R28 < 0), -(R28 / S28 - 1) ), "-" )} -> 0 | V28: {=IFERROR(_xlfn.XLOOKUP(1,(EMG_act!$C$2:$CI$2=V$12)*(EMG_act!$C$3:$CI$3=$D$8),EMG_act!$C$25:$CI$25),"n/a")} -> 2.774826 | W28: {=IF(AND(ISNUMBER(R28), ISNUMBER(V28)), _xlfn.IFS( AND(V28 < 0, R28 < 0, R28 > V28), R28 / V28 - 1, AND(V28 < 0, R28 < 0, R28 <= V28), -(R28 / V28 - 1), AND(V28 < 0, R28 > 0), -(R28 / V28 - 1), AND(V28 > 0, R28 > 0), -(R28 / V28 - 1), AND(V28 > 0, R28 < 0), -(R28 / V28 - 1) ), "-" )} -> -0.13194419
C30: KPIs | G30: Totals | K30: Year to date development | R30: Month to date development
C32: Share of online (Retail) | G32: =IFERROR(SUMIF(EMG_act!$C$2:$BA$2,G$12,EMG_act!$C61:$BA61)/SUMIF(EMG_act!$C$2:$BA$2,G$12,EMG_act!$C60:$BA60),"-") -> - | H32: =IFERROR(SUMIF(EMG_act!$C$2:$BA$2,H$12,EMG_act!$C61:$BA61)/SUMIF(EMG_act!$C$2:$BA$2,H$12,EMG_act!$C60:$BA60),"-") -> - | I32: =IFERROR(SUMIF(EMG_bud!$C$2:$BA$2,I$12,EMG_bud!$C61:$BA61)/SUMIF(EMG_bud!$C$2:$BA$2,I$12,EMG_bud!$C60:$BA60),"-") -> - | K32: =IFERROR(SUMIFS(EMG_act!$C61:$BA61,EMG_act!$C$2:$BA$2,K$12,EMG_act!$C$3:$BA$3,"<="&$D$8)/SUMIFS(EMG_act!$C60:$BA60,EMG_act!$C$2:$BA$2,K$12,EMG_act!$C$3:$BA$3,"<="&$D$8),"-") -> - | L32: =IFERROR(SUMIFS(EMG_bud!$C61:$BA61,EMG_bud!$C$2:$BA$2,L$12,EMG_bud!$C$3:$BA$3,"<="&$D$8)/SUMIFS(EMG_bud!$C60:$BA60,EMG_bud!$C$2:$BA$2,L$12,EMG_bud!$C$3:$BA$3,"<="&$D$8),"-") -> - | M32: =IF(OR(AND(K32<0,L32<0),AND(K32>0,L32<0)),-IFERROR(K32/L32-1,"-"),IFERROR(K32/L32-1,"-")) -> - | O32: =IFERROR(SUMIFS(EMG_act!$C61:$BA61,EMG_act!$C$2:$BA$2,O$12,EMG_act!$C$3:$BA$3,"<="&$D$8)/SUMIFS(EMG_act!$C60:$BA60,EMG_act!$C$2:$BA$2,O$12,EMG_act!$C$3:$BA$3,"<="&$D$8),"-") -> - | P32: =IF(OR(AND(K32<0,O32<0),AND(K32>0,O32<0)),-IFERROR(K32/O32-1,"-"),IFERROR(K32/O32-1,"-")) -> - | R32: =IFERROR(SUMIFS(EMG_act!$C61:$BA61,EMG_act!$C$2:$BA$2,R$12,EMG_act!$C$3:$BA$3,$D$8)/SUMIFS(EMG_act!$C60:$BA60,EMG_act!$C$2:$BA$2,R$12,EMG_act!$C$3:$BA$3,$D$8),"-") -> - | S32: =IFERROR(SUMIFS(EMG_bud!$C61:$BA61,EMG_bud!$C$2:$BA$2,R$12,EMG_bud!$C$3:$BA$3,$D$8)/SUMIFS(EMG_bud!$C60:$BA60,EMG_bud!$C$2:$BA$2,R$12,EMG_bud!$C$3:$BA$3,$D$8),"-") -> - | T32: =IF(OR(AND(R32<0,S32<0),AND(R32>0,S32<0)),-IFERROR(R32/S32-1,"-"),IFERROR(R32/S32-1,"-")) -> - | V32: =IFERROR(SUMIFS(EMG_act!$C61:$BA61,EMG_act!$C$2:$BA$2,V$12,EMG_act!$C$3:$BA$3,$D$8)/SUMIFS(EMG_act!$C60:$BA60,EMG_act!$C$2:$BA$2,V$12,EMG_act!$C$3:$BA$3,$D$8),"-") -> - | W32: =IF(OR(AND(R32<0,V32<0),AND(R32>0,V32<0)),-IFERROR(R32/V32-1,"-"),IFERROR(R32/V32-1,"-")) -> -
C33: # of published titles | G33: =IFERROR(SUMIF(EMG_act!$C$2:$BA$2,G$12,EMG_act!$C66:$BA66),"-") -> 0 | H33: =IFERROR(SUMIF(EMG_act!$C$2:$BA$2,H$12,EMG_act!$C66:$BA66),"-") -> 0 | I33: =IFERROR(SUMIF(EMG_bud!$C$2:$BA$2,I$12,EMG_bud!$C66:$BA66),"-") -> 0 | K33: =IFERROR(SUMIFS(EMG_act!$C66:$BA66,EMG_act!$C$2:$BA$2,K$12,EMG_act!$C$3:$BA$3,"<="&$D$8),"-") -> 0 | L33: =IFERROR(SUMIFS(EMG_bud!$C66:$BA66,EMG_bud!$C$2:$BA$2,L$12,EMG_bud!$C$3:$BA$3,"<="&$D$8),"-") -> 0 | M33: =IF(OR(AND(K33<0,L33<0),AND(K33>0,L33<0)),-IFERROR(K33/L33-1,"-"),IFERROR(K33/L33-1,"-")) -> - | O33: 383 | P33: =IF(OR(AND(K33<0,O33<0),AND(K33>0,O33<0)),-IFERROR(K33/O33-1,"-"),IFERROR(K33/O33-1,"-")) -> -1 | R33: =IFERROR(SUMIFS(EMG_act!$C66:$BA66,EMG_act!$C$2:$BA$2,R$12,EMG_act!$C$3:$BA$3,$D$8),"-") -> 0 | S33: ="-" -> - | T33: =IF(OR(AND(O33<0,S33<0),AND(O33>0,S33<0)),-IFERROR(O33/S33-1,"-"),IFERROR(O33/S33-1,"-")) -> - | V33: =IFERROR(SUMIFS(EMG_act!$C66:$BA66,EMG_act!$C$2:$BA$2,V$12,EMG_act!$C$3:$BA$3,$D$8),"-") -> 0 | W33: =IF(OR(AND(R33<0,V33<0),AND(R33>0,V33<0)),-IFERROR(R33/V33-1,"-"),IFERROR(R33/V33-1,"-")) -> -
C50: FY starts in: | D50: January
C52: Month | D52: CY month | E52: FY month
C53: January | D53: 1 | E53: =IF(C53=$D$50,1,E64+1) -> 1 | G53: ="E"&ROW(G53)&":" -> E53: | H53: ="E"&ROW(G53)+MATCH(12,E53:E64,0)-1 -> E64 | K53: {=INDIRECT(G53&H53)} -> 1
C54: February | D54: 2 | E54: =IF(C54=$D$50,1,E53+1) -> 2 | K54: 2
C55: March | D55: 3 | E55: =IF(C55=$D$50,1,E54+1) -> 3 | K55: 3
C56: April | D56: 4 | E56: =IF(C56=$D$50,1,E55+1) -> 4 | K56: 4
C57: May | D57: 5 | E57: =IF(C57=$D$50,1,E56+1) -> 5 | K57: 5
C58: June | D58: 6 | E58: =IF(C58=$D$50,1,E57+1) -> 6 | K58: 6
C59: July | D59: 7 | E59: =IF(C59=$D$50,1,E58+1) -> 7 | K59: 7
C60: August | D60: 8 | E60: =IF(C60=$D$50,1,E59+1) -> 8 | K60: 8
C61: September | D61: 9 | E61: =IF(C61=$D$50,1,E60+1) -> 9 | K61: 9
C62: October | D62: 10 | E62: =IF(C62=$D$50,1,E61+1) -> 10 | K62: 10
C63: November | D63: 11 | E63: =IF(C63=$D$50,1,E62+1) -> 11 | K63: 11
C64: December | D64: 12 | E64: =IF(C64=$D$50,1,E63+1) -> 12 | K64: 12

Sheet Sources --->

Sheet FX
B3: CZK/EUR
B4: 2021 | C4: 2022 | D4: 2023
B5: 25.645 | C5: 24.565 | D5: 24.165

Sheet EMG_act
B2: Fiscal/Financial year | C2: =C10 -> 20 | D2: =C10 -> 20 | E2: =C10 -> 20 | F2: =C10 -> 20 | G2: =C10 -> 20 | H2: =C10 -> 20 | I2: =C10 -> 20 | J2: =C10 -> 20 | K2: =C10 -> 20 | L2: =C10 -> 20 | M2: =C10 -> 20 | N2: =C10 -> 20 | O2: =O10 -> 21 | P2: =O10 -> 21 | Q2: =O10 -> 21 | R2: =O10 -> 21 | S2: =O10 -> 21 | T2: =O10 -> 21 | U2: =O10 -> 21 | V2: =O10 -> 21 | W2: =O10 -> 21 | X2: =O10 -> 21 | Y2: =O10 -> 21 | Z2: =O10 -> 21 | AA2: =AA10 -> 22 | AB2: =AA10 -> 22 | AC2: =AA10 -> 22 | AD2: =AA10 -> 22 | AE2: =AA10 -> 22 | AF2: =AA10 -> 22 | AG2: =AA10 -> 22 | AH2: =AA10 -> 22 | AI2: =AA10 -> 22 | AJ2: =AA10 -> 22 | AK2: =AA10 -> 22 | AL2: =AA10 -> 22 | AM2: =AM10 -> 23 | AN2: =AM2 -> 23 | AO2: =AN2 -> 23 | AP2: =AO2 -> 23 | AQ2: =AP2 -> 23 | AR2: =AQ2 -> 23 | AS2: =AR2 -> 23 | AT2: =AS2 -> 23 | AU2: =AT2 -> 23 | ... AX2: =AW2 -> 23 | AY2: =AY10 -> 24 | AZ2: =AY2 -> 24 | BA2: =AZ2 -> 24 | BB2: =BA2 -> 24 | BC2: =BB2 -> 24 | BD2: =BC2 -> 24 | BE2: =BD2 -> 24 | BF2: =BE2 -> 24 | BG2: =BF2 -> 24 | ... BJ2: =BI2 -> 24 | BK2: =BK10 -> 25 | BL2: =BK2 -> 25 | BM2: =BL2 -> 25 | BN2: =BM2 -> 25 | BO2: =BN2 -> 25 | BP2: =BO2 -> 25 | BQ2: =BP2 -> 25 | BR2: =BQ2 -> 25 | BS2: =BR2 -> 25 | ... BV2: =BU2 -> 25 | BW2: =BW10 -> 26 | BX2: =BW2 -> 26 | BY2: =BX2 -> 26 | BZ2: =BY2 -> 26 | CA2: =BZ2 -> 26 | CB2: =CA2 -> 26 | CC2: =CB2 -> 26 | CD2: =CC2 -> 26 | CE2: =CD2 -> 26 | ... CH2: =CG2 -> 26
B3: FY month number | C3: 1 | D3: 2 | E3: 3 | F3: 4 | G3: 5 | H3: 6 | I3: 7 | J3: 8 | K3: 9 | L3: 10 | M3: 11 | N3: 12 | O3: 1 | P3: 2 | Q3: 3 | R3: 4 | S3: 5 | T3: 6 | U3: 7 | V3: 8 | W3: 9 | X3: 10 | Y3: 11 | Z3: 12 | AA3: 1 | AB3: 2 | AC3: 3 | AD3: 4 | AE3: 5 | AF3: 6 | AG3: 7 | AH3: 8 | AI3: 9 | AJ3: 10 | AK3: 11 | AL3: 12 | AM3: 1 | AN3: 2 | AO3: 3 | AP3: 4 | AQ3: 5 | AR3: 6 | AS3: 7 | AT3: 8 | AU3: 9 | AV3: 10 | AW3: 11 | AX3: 12 | AY3: 1 | AZ3: 2 | BA3: 3 | BB3: 4 | BC3: 5 | BD3: 6 | BE3: 7 | BF3: 8 | BG3: 9 | BH3: 10 | BI3: 11 | BJ3: 12 | BK3: 1 | BL3: 2 | BM3: 3 | BN3: 4 | BO3: 5 | BP3: 6 | BQ3: 7 | BR3: 8 | BS3: 9 | BT3: 10 | BU3: 11 | BV3: 12 | BW3: 1 | BX3: 2 | BY3: 3 | BZ3: 4 | CA3: 5 | CB3: 6 | CC3: 7 | CD3: 8 | CE3: 9 | CF3: 10 | CG3: 11 | CH3: 12
B5: Calendar year | C5: 2020 | D5: =IF(C6<D6,C5,C5+1) -> 2020 | E5: =IF(D6<E6,D5,D5+1) -> 2020 | F5: =IF(E6<F6,E5,E5+1) -> 2020 | G5: =IF(F6<G6,F5,F5+1) -> 2020 | H5: =IF(G6<H6,G5,G5+1) -> 2020 | I5: =IF(H6<I6,H5,H5+1) -> 2020 | J5: =IF(I6<J6,I5,I5+1) -> 2020 | K5: =IF(J6<K6,J5,J5+1) -> 2020 | ... CH5: =IF(CG6<CH6,CG5,CG5+1) -> 2026
B6: Calendar month number | C6: =INDEX(EMG!$D$53:$D$64,MATCH(C$3,EMG!$E$53:$E$64,0),1) -> 1 | D6: =INDEX(EMG!$D$53:$D$64,MATCH(D$3,EMG!$E$53:$E$64,0),1) -> 2 | E6: =INDEX(EMG!$D$53:$D$64,MATCH(E$3,EMG!$E$53:$E$64,0),1) -> 3 | F6: =INDEX(EMG!$D$53:$D$64,MATCH(F$3,EMG!$E$53:$E$64,0),1) -> 4 | G6: =INDEX(EMG!$D$53:$D$64,MATCH(G$3,EMG!$E$53:$E$64,0),1) -> 5 | H6: =INDEX(EMG!$D$53:$D$64,MATCH(H$3,EMG!$E$53:$E$64,0),1) -> 6 | I6: =INDEX(EMG!$D$53:$D$64,MATCH(I$3,EMG!$E$53:$E$64,0),1) -> 7 | J6: =INDEX(EMG!$D$53:$D$64,MATCH(J$3,EMG!$E$53:$E$64,0),1) -> 8 | ... BV6: =INDEX(EMG!$D$53:$D$64,MATCH(BV$3,EMG!$E$53:$E$64,0),1) -> 12 | BW6: 1 | BX6: 2 | BY6: 3 | BZ6: 4 | CA6: 5 | CB6: 6 | CC6: 7 | CD6: 8 | CE6: 9 | CF6: 10 | CG6: 11 | CH6: 12
B9: ACTUALS
C10: =IF(C6=1,C5-2000,C5-2000+1) -> 20 | O10: =IF(O6=1,O5-2000,O5-2000+1) -> 21 | AA10: =IF(AA6=1,AA5-2000,AA5-2000+1) -> 22 | AM10: =IF(AM6=1,AM5-2000,AM5-2000+1) -> 23 | AY10: =IF(AY6=1,AY5-2000,AY5-2000+1) -> 24 | BK10: =IF(BK6=1,BK5-2000,BK5-2000+1) -> 25 | BW10: =IF(BW6=1,BW5-2000,BW5-2000+1) -> 26
B11: CZK million (unless otherwise stated) | C11: =DATE(C5,C6,1) -> 43831 | D11: =DATE(D5,D6,1) -> 43862 | E11: =DATE(E5,E6,1) -> 43891 | F11: =DATE(F5,F6,1) -> 43922 | G11: =DATE(G5,G6,1) -> 43952 | H11: =DATE(H5,H6,1) -> 43983 | I11: =DATE(I5,I6,1) -> 44013 | J11: =DATE(J5,J6,1) -> 44044 | ... CH11: =DATE(CH5,CH6,1) -> 46357
B12: Retail | BT12: 0 | BU12: 0 | BV12: 0 | BW12: 0 | BX12: 0
B13: Distribution | BT13: 0 | BU13: 0 | BV13: 0 | BW13: 0 | BX13: 0
B14: Publishing | BT14: 0 | BU14: 0 | BV14: 0 | BW14: 0 | BX14: 0
B15: Elimination | BT15: 0 | BU15: 0 | BV15: 0 | BW15: 0 | BX15: 0
B16: CONSOLIDATED REVENUES | C16: 0 | D16: 0 | E16: 0 | F16: 0 | G16: 0 | H16: 0 | I16: 0 | J16: 0 | K16: 0 | L16: 0 | M16: 0 | N16: 0 | O16: 0 | P16: 0 | Q16: 0 | R16: 0 | S16: 0 | T16: 0 | U16: 0 | V16: 0 | W16: 0 | X16: 0 | Y16: 0 | Z16: 0 | AA16: 122 | AB16: 94 | AC16: 249 | AD16: 153 | AE16: 37 | AF16: 151 | AG16: 267 | AH16: 232 | AI16: 237 | AJ16: 188 | AK16: 17 | AL16: 209 | AM16: 300 | AN16: 147 | AO16: 88 | AP16: 48 | AQ16: 138 | AR16: 268 | AS16: 159 | AT16: 64 | AU16: 66 | AV16: 32 | AW16: 231 | AX16: 107 | AY16: 54 | AZ16: 1 | BA16: 7 | BB16: 124 | BC16: 149 | BD16: 67 | BE16: 277 | BF16: 19 | BG16: 52 | BH16: 116 | BI16: 2 | BJ16: 190 | BK16: 185 | BL16: 74 | BM16: 102 | BN16: 188 | BO16: 216 | BP16: 93 | BQ16: 206 | BR16: 106 | BS16: 179 | BT16: 55 | BU16: 269 | BV16: 117 | BW16: 12 | BX16: 86
B17: Gross Margin | C17: 7 | D17: 22 | E17: 31 | F17: 64 | G17: 98 | H17: 70 | I17: 34 | J17: 30 | K17: 41 | L17: 11 | M17: 100 | N17: 81 | O17: 63 | P17: 92 | Q17: 28 | R17: 50 | S17: 70 | T17: 98 | U17: 66 | V17: 35 | W17: 51 | X17: 5 | Y17: 7 | Z17: 7 | AA17: 16 | AB17: 43 | AC17: 81 | AD17: 39 | AE17: 62 | AF17: 98 | AG17: 81 | AH17: 69 | AI17: 41 | AJ17: 34 | AK17: 67 | AL17: 69 | AM17: 38 | AN17: 99 | AO17: 80 | AP17: 60 | AQ17: 54 | AR17: 74 | AS17: 16 | AT17: 42 | AU17: 92 | AV17: 21 | AW17: 39 | AX17: 10 | AY17: 11 | AZ17: 79 | BA17: 25 | BB17: 75 | BC17: 59 | BD17: 47 | BE17: 91 | BF17: 23 | BG17: 58 | BH17: 17 | BI17: 25 | BJ17: 23 | BK17: 96 | BL17: 75 | BM17: 91 | BN17: 97 | BO17: 94 | BP17: 65 | BQ17: 44 | BR17: 52 | BS17: 47 | BT17: 24 | BU17: 93 | BV17: 26 | BW17: 45 | BX17: 17
B18: % of Revenues | C18: #DIV/0! | D18: #DIV/0! | E18: #DIV/0! | F18: #DIV/0! | G18: #DIV/0! | H18: #DIV/0! | I18: #DIV/0! | J18: #DIV/0! | K18: #DIV/0! | L18: #DIV/0! | M18: #DIV/0! | N18: #DIV/0! | O18: #DIV/0! | P18: #DIV/0! | Q18: #DIV/0! | R18: #DIV/0! | S18: #DIV/0! | T18: #DIV/0! | U18: #DIV/0! | V18: #DIV/0! | W18: #DIV/0! | X18: #DIV/0! | Y18: #DIV/0! | Z18: #DIV/0! | AA18: 0.13114754 | AB18: 0.45744681 | AC18: 0.3253012 | AD18: 0.25490196 | AE18: 1.6756757 | AF18: 0.64900662 | AG18: 0.30337079 | AH18: 0.29741379 | AI18: 0.17299578 | AJ18: 0.18085106 | AK18: 3.9411765 | AL18: 0.33014354 | AM18: 0.12666667 | AN18: 0.67346939 | AO18: 0.90909091 | AP18: 1.25 | AQ18: 0.39130435 | AR18: 0.2761194 | AS18: 0.10062893 | AT18: 0.65625 | AU18: 1.3939394 | AV18: 0.65625 | AW18: 0.16883117 | AX18: 0.093457944 | AY18: 0.2037037 | AZ18: 79 | BA18: 3.5714286 | BB18: 0.60483871 | BC18: 0.39597315 | BD18: 0.70149254 | BE18: 0.32851986 | BF18: 1.2105263 | BG18: 1.1153846 | BH18: 0.14655172 | BI18: 12.5 | BJ18: 0.12105263 | BK18: 0.37449263 | BL18: 0.36167017 | BM18: 0.36721414 | BN18: 0.3598879 | BO18: 0.37950756 | BP18: 0.38628966 | BQ18: 0.37891805 | BR18: 0.36598393 | BS18: 0.35850634 | BT18: 0.36980752 | BU18: 0.36046538 | BV18: 0.39657846 | BW18: 0.35374369 | BX18: 0.36701163
B19: REP. EBITDA (Excl. Licence Depreciation) | C19: 7 | D19: 6 | E19: 37 | F19: 45 | G19: 28 | H19: 16 | I19: 17 | J19: 35 | K19: 16 | L19: 12 | M19: 10 | N19: 21 | O19: 12 | P19: 8 | Q19: 3 | R19: 19 | S19: 27 | T19: 42 | U19: 49 | V19: 36 | W19: 3 | X19: 19 | Y19: 32 | Z19: 37 | AA19: 34 | AB19: 41 | AC19: 45 | AD19: 38 | AE19: 23 | AF19: 8 | AG19: 21 | AH19: 28 | AI19: 39 | AJ19: 35 | AK19: 18 | AL19: 38 | AM19: 39 | AN19: 32 | AO19: 19 | AP19: 44 | AQ19: 7 | AR19: 25 | AS19: 1 | AT19: 38 | AU19: 45 | AV19: 21 | AW19: 7 | AX19: 35 | AY19: 4 | AZ19: 4 | BA19: 10 | BB19: 45 | BC19: 18 | BD19: 34 | BE19: 47 | BF19: 22 | BG19: 20 | BH19: 49 | BI19: 21 | BJ19: 1 | BK19: 37 | BL19: 3 | BM19: 21 | BN19: 47 | BO19: 46 | BP19: 27 | BQ19: 0 | BR19: 47 | BS19: 4 | BT19: 38 | BU19: 40 | BV19: 2 | BW19: 19 | BX19: 41
B20: % of Revenues | C20: #DIV/0! | D20: #DIV/0! | E20: #DIV/0! | F20: #DIV/0! | G20: #DIV/0! | H20: #DIV/0! | I20: #DIV/0! | J20: #DIV/0! | K20: #DIV/0! | L20: #DIV/0! | M20: #DIV/0! | N20: #DIV/0! | O20: #DIV/0! | P20: #DIV/0! | Q20: #DIV/0! | R20: #DIV/0! | S20: #DIV/0! | T20: #DIV/0! | U20: #DIV/0! | V20: #DIV/0! | W20: #DIV/0! | X20: #DIV/0! | Y20: #DIV/0! | Z20: #DIV/0! | AA20: 0.27868852 | AB20: 0.43617021 | AC20: 0.18072289 | AD20: 0.24836601 | AE20: 0.62162162 | AF20: 0.052980132 | AG20: 0.078651685 | AH20: 0.12068966 | AI20: 0.16455696 | AJ20: 0.18617021 | AK20: 1.0588235 | AL20: 0.18181818 | AM20: 0.13 | AN20: 0.21768707 | AO20: 0.21590909 | AP20: 0.91666667 | AQ20: 0.050724638 | AR20: 0.093283582 | AS20: 0.0062893082 | AT20: 0.59375 | AU20: 0.68181818 | AV20: 0.65625 | AW20: 0.03030303 | AX20: 0.3271028 | AY20: 0.074074074 | AZ20: 4 | BA20: 1.4285714 | BB20: 0.36290323 | BC20: 0.12080537 | BD20: 0.50746269 | BE20: 0.16967509 | BF20: 1.1578947 | BG20: 0.38461538 | BH20: 0.42241379 | BI20: 10.5 | BJ20: 0.0052631579 | BK20: 0.051978575 | BL20: -0.012041004 | BM20: 0.0025599612 | BN20: -0.016940532 | BO20: -0.020035975 | BP20: 0.025115864 | BQ20: 0.014414341 | BR20: 0.019856508 | BS20: 0.12269235 | BT20: 0.11640395 | BU20: 0.12455088 | BV20: 0.21303006 | BW20: 0.001512005 | BX20: -0.0077679233
B21: CAPEX | C21: 12 | D21: 11 | E21: 7 | F21: 4 | G21: 16 | H21: 2 | I21: 5 | J21: 0 | K21: 2 | L21: 10 | M21: 19 | N21: 5 | O21: 3 | P21: 9 | Q21: 18 | R21: 11 | S21: 18 | T21: 0 | U21: 5 | V21: 5 | W21: 5 | X21: 18 | Y21: 12 | Z21: 13 | AA21: 3 | AB21: 6 | AC21: 0 | AD21: 4 | AE21: 7 | AF21: 20 | AG21: 12 | AH21: 7 | AI21: 11 | AJ21: 6 | AK21: 17 | AL21: 3 | AM21: 7 | AN21: 18 | AO21: 6 | AP21: 9 | AQ21: 16 | AR21: 18 | AS21: 18 | AT21: 13 | AU21: 1 | AV21: 10 | AW21: 18 | AX21: 17 | AY21: 16 | AZ21: 10 | BA21: 13 | BB21: 12 | BC21: 6 | BD21: 2 | BE21: 1 | BF21: 14 | BG21: 10 | BH21: 12 | BI21: 19 | BJ21: 15 | BK21: 6 | BL21: 3 | BM21: 19 | BN21: 4 | BO21: 2 | BP21: 13 | BQ21: 1 | BR21: 12 | BS21: 12 | BT21: 17 | BU21: 16 | BV21: 3 | BW21: 10 | BX21: 9
B22: NET DEBT | C22: 921 | D22: 910 | E22: 874 | F22: 920 | G22: 957 | H22: 906 | I22: 915 | J22: 955 | K22: 924 | L22: 967 | M22: 964 | N22: 874 | O22: 909 | P22: 875 | Q22: 947 | R22: 947 | S22: 962 | T22: 891 | U22: 900 | V22: 886 | W22: 954 | X22: 874 | Y22: 888 | Z22: 895 | AA22: 902 | AB22: 893 | AC22: 962 | AD22: 944 | AE22: 924 | AF22: 916 | AG22: 957 | AH22: 916 | AI22: 926 | AJ22: 944 | AK22: 878 | AL22: 961 | AM22: 888 | AN22: 927 | AO22: 937 | AP22: 895 | AQ22: 941 | AR22: 959 | AS22: 891 | AT22: 901 | AU22: 921 | AV22: 875 | AW22: 942 | AX22: 942 | AY22: 956 | AZ22: 895 | BA22: 933 | BB22: 876 | BC22: 884 | BD22: 925 | BE22: 913 | BF22: 943 | BG22: 915 | BH22: 934 | BI22: 883 | BJ22: 957 | BK22: 965 | BL22: 928 | BM22: 965 | BN22: 968 | BO22: 918 | BP22: 933 | BQ22: 914 | BR22: 940 | BS22: 962 | BT22: 950 | BU22: 945 | BV22: 959 | BW22: 970 | BX22: 893
B23: Debt | C23: 972 | D23: 972 | E23: 972 | F23: 972 | G23: 972 | H23: 972 | I23: 972 | J23: 972 | K23: 972 | L23: 972 | M23: 972 | N23: 972 | O23: 972 | P23: 972 | Q23: 972 | R23: 972 | S23: 972 | T23: 972 | U23: 972 | V23: 972 | W23: 972 | X23: 972 | Y23: 972 | Z23: 972 | AA23: 972 | AB23: 972 | AC23: 972 | AD23: 972 | AE23: 972 | AF23: 972 | AG23: 972 | AH23: 972 | AI23: 972 | AJ23: 972 | AK23: 972 | AL23: 972 | AM23: 972 | AN23: 972 | AO23: 972 | AP23: 972 | AQ23: 972 | AR23: 972 | AS23: 972 | AT23: 972 | AU23: 972 | AV23: 972 | AW23: 972 | AX23: 972 | AY23: 972 | AZ23: 972 | BA23: 972 | BB23: 972 | BC23: 972 | BD23: 972 | BE23: 972 | BF23: 972 | BG23: 972 | BH23: 972 | BI23: 972 | BJ23: 972 | BK23: 972 | BL23: 972 | BM23: 972 | BN23: 972 | BO23: 972 | BP23: 972 | BQ23: 972 | BR23: 972 | BS23: 972 | BT23: 972 | BU23: 972 | BV23: 972 | BW23: 972 | BX23: 972
B24: Cash | C24: 51 | D24: 62 | E24: 98 | F24: 52 | G24: 15 | H24: 66 | I24: 57 | J24: 17 | K24: 48 | L24: 5 | M24: 8 | N24: 98 | O24: 63 | P24: 97 | Q24: 25 | R24: 25 | S24: 10 | T24: 81 | U24: 72 | V24: 86 | W24: 18 | X24: 98 | Y24: 84 | Z24: 77 | AA24: 70 | AB24: 79 | AC24: 10 | AD24: 28 | AE24: 48 | AF24: 56 | AG24: 15 | AH24: 56 | AI24: 46 | AJ24: 28 | AK24: 94 | AL24: 11 | AM24: 84 | AN24: 45 | AO24: 35 | AP24: 77 | AQ24: 31 | AR24: 13 | AS24: 81 | AT24: 71 | AU24: 51 | AV24: 97 | AW24: 30 | AX24: 30 | AY24: 16 | AZ24: 77 | BA24: 39 | BB24: 96 | BC24: 88 | BD24: 47 | BE24: 59 | BF24: 29 | BG24: 57 | BH24: 38 | BI24: 89 | BJ24: 15 | BK24: 7 | BL24: 44 | BM24: 7 | BN24: 4 | BO24: 54 | BP24: 39 | BQ24: 58 | BR24: 32 | BS24: 10 | BT24: 22 | BU24: 27 | BV24: 13 | BW24: 2 | BX24: 79
B25: Net Debt / LTM EBITDA | O25: 3.5647059 | P25: 3.4046693 | Q25: 4.2466368 | R25: 4.8071066 | S25: 4.9081633 | T25: 4.0135135 | U25: 3.5433071 | V25: 3.4745098 | W25: 3.9421488 | X25: 3.5100402 | Y25: 3.2767528 | Z25: 3.1184669 | AA25: 2.9190939 | AB25: 2.6111111 | AC25: 2.5052083 | AD25: 2.3424318 | AE25: 2.3157895 | AF25: 2.509589 | AG25: 2.8397626 | AH25: 2.7841945 | AI25: 2.5369863 | AJ25: 2.4776903 | AK25: 2.3923706 | AL25: 2.611413 | AM25: 2.6571838 | AN25: 3.1780362 | AO25: 3.9056928 | AP25: 4.3562408 | AQ25: 5.3535449 | AR25: 5.7310627 | AS25: 6.3921174 | AT25: 7.6875169 | AU25: 10.101486 | AV25: 11.420379 | AW25: 8.7525127 | AX25: 4.6911393 | AY25: 4.6219188 | AZ25: 4.1551306 | BA25: 3.9670537 | BB25: 3.1080081 | BC25: 2.8367889 | BD25: 2.6494802 | BE25: 2.2194278 | BF25: 2.198625 | BG25: 2.0868809 | BH25: 2.0054135 | BI25: 2.0240357 | BJ25: 3.1114578 | BK25: 2.8511161 | BL25: 2.774826 | BM25: 2.8174054 | BN25: 2.8523898 | BO25: 2.5331182 | BP25: 2.7852828 | BQ25: 2.6989215 | BR25: 2.8004509 | BS25: 2.7325368 | BT25: 2.5538796 | BU25: 2.9423066 | BV25: 2.9423529 | BW25: 3.3540635 | BX25: 3.1409482
B29: Adjusted EBITDA ACTUAL | C29: =C19-C68 -> 7 | D29: =D19-D68 -> 6 | E29: =E19-E68 -> 37 | F29: =F19-F68 -> 45 | G29: =G19-G68 -> 28 | H29: =H19-H68 -> 16 | I29: =I19-I68 -> 17 | J29: =J19-J68 -> 35 | ... AL29: =AL19-AL68 -> 38 | AM29: 0.18839562 | AN29: -1.4988325 | AO29: -6.7833396 | AP29: 3.5461494 | AQ29: -6.6809882 | AR29: -0.43767068 | AS29: -6.9432832 | AT29: 5.8125631 | AU29: 12.971713 | AV29: 20.442712 | AW29: 49.008817 | AX29: 131.17786 | AY29: =AY19-AY68 -> 6.2248 | AZ29: =AZ19-AZ68 -> 7.0570248 | BA29: =BA19-BA68 -> 13.007438 | BB29: =BB19-BB68 -> 50.211561 | BC29: =BC19-BC68 -> 23.086412 | BD29: =BD19-BD68 -> 37.067461 | BE29: =BE19-BE68 -> 55.298921 | BF29: =BF19-BF68 -> 23.34971 | ... BV29: =BV19-BV68 -> 7.2466538 | BW29: 0.38768757 | BX29: -1.8639256
B31: Net debt
B32: Luxor - Bank loans and borrowings | C32: 0 | D32: 0 | E32: 0 | F32: 0 | G32: 0 | H32: 0 | I32: 0 | J32: 0 | K32: 0 | L32: 0 | M32: 0 | N32: 0
B33: Luxor - Short-term Bank loans and borrowings | C33: 0 | D33: 0 | E33: 0 | F33: 0 | G33: 0 | H33: 0 | I33: 0 | J33: 0 | K33: 0 | L33: 0 | M33: 0 | N33: 49.712788
B34: EMG - Bank loans and borrowings | C34: 280.84279 | D34: 280.84279 | E34: 282.45986 | F34: 282.45986 | G34: 282.45986 | H34: 275.66476 | I34: 275.66476 | J34: 275.66476 | K34: 268.0152 | L34: 268.0152 | M34: 268.0152 | N34: 209.46826
B35: EMG - Short-term Bank loans and borrowings RCF | C35: 172.54054 | D35: 188.11036 | E35: 172.54082 | F35: 176.14945 | G35: 177.76552 | H35: 179.19737 | I35: 178.65195 | J35: 175.0084 | K35: 189.81103 | L35: 185.58097 | M35: 145.5944 | N35: 20.851309
B36: EMG - Short-term part of Long term Bank loans | C36: 81.496 | D36: 81.496 | E36: 81.496 | F36: 81.496 | G36: 81.496 | H36: 81.496 | I36: 81.496 | J36: 81.496 | K36: 81.496 | L36: 81.496 | M36: 81.496 | N36: 81.496
B37: Other debt 1 | C37: 250 | D37: 250 | E37: 250 | F37: 250 | G37: 250 | H37: 250 | I37: 250 | J37: 250 | K37: 250 | L37: 250 | M37: 250 | N37: 250
B38: Other debt 3 | C38: =#REF! -> #REF! | D38: =C38 -> #REF! | E38: =D38 -> #REF! | F38: =E38 -> #REF! | G38: =F38 -> #REF! | H38: =G38 -> #REF! | I38: =H38 -> #REF! | J38: =I38 -> #REF! | K38: =J38 -> #REF! | ... M38: =L38 -> #REF! | N38: 42.2
B39: Cash - EMG | C39: -2.868183 | D39: -1.9863696 | E39: -2.1567572 | F39: -2.1503019 | G39: -2.2937383 | H39: -2.8316491 | I39: -1.5852881 | J39: -2.421462 | K39: -3.6642329 | L39: -4.0446726 | M39: -6.6243026 | N39: -2.0907474
B40: Cash - Luxor | C40: -10.177826 | D40: -9.7954163 | E40: -15.311255 | F40: -4.7882101 | G40: -27.57222 | H40: -30.947836 | I40: -15.849871 | J40: -21.498443 | K40: -16.438302 | L40: -15.562625 | M40: -16.647389 | N40: -32.184791
B41: TOTAL | C41: =SUM(C32:C40) -> #REF! | D41: =SUM(D32:D40) -> #REF! | E41: =SUM(E32:E40) -> #REF! | F41: =SUM(F32:F40) -> #REF! | G41: =SUM(G32:G40) -> #REF! | H41: =SUM(H32:H40) -> #REF! | I41: =SUM(I32:I40) -> #REF! | J41: =SUM(J32:J40) -> #REF! | ... U41: =SUM(U32:U40) -> 0
B46: in thousands EUR
B48: EMG GM | C48: 34797.902 | D48: 34072.605 | E48: 20343.815 | F48: 27709.68 | G48: 32363.371 | H48: 38684.163 | I48: 34872.275 | J48: 35363.672 | K48: 50550.573 | L48: 48447.559 | M48: 66291.333 | N48: 137015.49 | O48: 34787.257 | P48: 26830.029 | Q48: 37180.822 | R48: 35204.499 | S48: 46293.348 | T48: 43917.69 | U48: 46845.439 | AA48: 34787.257 | AB48: 26830.029 | AC48: 37180.822 | AD48: 35204.499 | AE48: 46293.348 | AF48: 43917.69 | AG48: 46845.439 | AM48: 34787.257 | AN48: 26830.029 | AO48: 37180.822 | AP48: 35204.499 | AQ48: 46293.348 | AR48: 43917.69 | AS48: 46845.439
B49: NLX GM | C49: 23586.605 | D49: 19517.574 | E49: 10117.865 | F49: 3192.5379 | G49: 14178.802 | H49: 19485.788 | I49: 21371.554 | J49: 20585.819 | K49: 25082.564 | L49: 18068.188 | M49: 12365.323 | N49: 66447.14 | O49: 7918.2524 | P49: 6287.2008 | Q49: 7196.4639 | R49: 4454.4093 | S49: 20679.907 | T49: 23545.347 | U49: 26388.097 | AA49: 7918.2524 | AB49: 6287.2008 | AC49: 7196.4639 | AD49: 4454.4093 | AE49: 20679.907 | AF49: 23545.347 | AG49: 26388.097 | AM49: 7918.2524 | AN49: 6287.2008 | AO49: 7196.4639 | AP49: 4454.4093 | AQ49: 20679.907 | AR49: 23545.347 | AS49: 26388.097
B50: TOTAL | C50: =SUM(C48:C49) -> 58384.507 | D50: =SUM(D48:D49) -> 53590.179 | E50: =SUM(E48:E49) -> 30461.68 | F50: =SUM(F48:F49) -> 30902.218 | G50: =SUM(G48:G49) -> 46542.173 | H50: =SUM(H48:H49) -> 58169.951 | I50: =SUM(I48:I49) -> 56243.829 | J50: =SUM(J48:J49) -> 55949.491 | ... AL50: =SUM(AL48:AL49) -> 0 | AM50: 42705.51 | AN50: 33117.23 | AO50: 44377.286 | AP50: 39658.908 | AQ50: 66973.255 | AR50: 67463.037 | AS50: 73233.536 | AT50: 0 | AU50: 0 | AV50: 0 | AW50: 0 | AX50: 0
B53: EMG EBITDA | C53: 1284.2371 | D53: 1992.6704 | E53: -25.86552 | F53: 6297.4676 | G53: 5346.971 | H53: 11098.015 | I53: 6486.2783 | J53: 4838.8765 | K53: 16089.369 | L53: 10271.009 | M53: 21123.224 | N53: 89258.735 | O53: 7031.5844 | P53: 2193.013 | Q53: 6311.2836 | R53: 8746.3507 | S53: 14105.644 | T53: 12243.299 | U53: 19237.388 | AA53: 7031.5844 | AB53: 2193.013 | AC53: 6311.2836 | AD53: 8746.3507 | AE53: 14105.644 | AF53: 12243.299 | AG53: 19237.388 | AM53: 7031.5844 | AN53: 2193.013 | AO53: 6311.2836 | AP53: 8746.3507 | AQ53: 14105.644 | AR53: 12243.299 | AS53: 19237.388
B54: NLX EBITDA | C54: -2250.4292 | D54: -5615.5915 | E54: -23351.916 | F54: -23790.159 | G54: -5846.0492 | H54: -6666.06 | I54: -3570.4624 | J54: -6617.0299 | K54: 2285.2415 | L54: -300.5664 | M54: -11825.152 | N54: 54351.128 | O54: -15584.298 | P54: -16983.86 | Q54: -11848.929 | R54: -17598.981 | S54: 23517.522 | T54: -2328.4376 | U54: -3621.5804 | AA54: -15584.298 | AB54: -16983.86 | AC54: -11848.929 | AD54: -17598.981 | AE54: 23517.522 | AF54: -2328.4376 | AG54: -3621.5804 | AM54: -15584.298 | AN54: -16983.86 | AO54: -11848.929 | AP54: -17598.981 | AQ54: 23517.522 | AR54: -2328.4376 | AS54: -3621.5804
B55: TOTAL | C55: =SUM(C53:C54) -> -966.19213 | D55: =SUM(D53:D54) -> -3622.9211 | E55: =SUM(E53:E54) -> -23377.782 | F55: =SUM(F53:F54) -> -17492.692 | G55: =SUM(G53:G54) -> -499.0782 | H55: =SUM(H53:H54) -> 4431.955 | I55: =SUM(I53:I54) -> 2915.8159 | J55: =SUM(J53:J54) -> -1778.1535 | ... AL55: =SUM(AL53:AL54) -> 0 | AM55: -8552.7135 | AN55: -14790.847 | AO55: -5537.6449 | AP55: -8852.6304 | AQ55: 37623.167 | AR55: 9914.8613 | AS55: 15615.807 | AT55: 0 | AU55: 0 | AV55: 0 | AW55: 0 | AX55: 0
B60: B2C revenues total (NLX, KK, BT) | O60: 52.707756 | P60: 53.037658 | Q60: 63.107429 | R60: 58.863133 | S60: 94.454988 | T60: 101.59562 | U60: 101.32745 | V60: 107.14763 | W60: 147.33618 | X60: 132.77134 | Y60: 215.70267 | Z60: 335.11542 | AA60: 93.910298 | AB60: 90.224407 | AC60: 90.87431 | AD60: 103.29241 | AE60: 96.686268 | AF60: 121.12409 | AG60: 107.70193 | AH60: 124.04144 | AI60: 152.46837 | AJ60: 139.97032 | AK60: 236.34544 | AL60: 379.42962 | AM60: 113.73019 | AN60: 104.12028 | AO60: 105.22571 | AP60: 116.00071 | AQ60: 107.99653 | AR60: 117.18825 | AS60: 108.40903 | AT60: 122.96567 | AU60: 144.07931 | AV60: 153.09804 | AW60: 224.77566 | AX60: 402.62975
B61: On-line revenues (KK on-line, BT, NLX on-line včetně BOPS) | O61: 41.105715 | P61: 39.324134 | Q61: 51.890036 | R61: 40.994364 | S61: 35.271322 | T61: 32.029012 | U61: 33.353793 | V61: 37.07949 | W61: 54.488006 | X61: 50.067123 | Y61: 79.788117 | Z61: 98.837002 | AA61: 31.861052 | AB61: 30.853802 | AC61: 29.934645 | AD61: 30.557728 | AE61: 28.437464 | AF61: 31.988826 | AG61: 28.615917 | AH61: 38.243042 | AI61: 51.75045 | AJ61: 47.740837 | AK61: 87.866549 | AL61: 104.06652 | AM61: 30.917745 | AN61: 28.810759 | AO61: 29.172433 | AP61: 32.173242 | AQ61: 34.345852 | AR61: 29.06954 | AS61: 26.925941 | AT61: 34.07081 | AU61: 43.327483 | AV61: 52.420752 | AW61: 79.196449 | AX61: 114.78476
B64: Share of online | O64: =O61/O60 -> 0.77987982 | P64: =P61/P60 -> 0.74143798 | Q64: =Q61/Q60 -> 0.82224924 | R64: =R61/R60 -> 0.6964353 | S64: =S61/S60 -> 0.37341937 | T64: =T61/T60 -> 0.31525978 | U64: =U61/U60 -> 0.3291684 | V64: =V61/V60 -> 0.34605983 | ... AL64: =AL61/AL60 -> 0.27427093 | AM64: 0.2718517 | AN64: 0.2767065 | AO64: 0.27723675 | AP64: 0.27735384 | AQ64: 0.31802737 | AR64: 0.24805849 | AS64: 0.24837359 | AT64: 0.27707579 | AU64: 0.30071968 | AV64: 0.34239989 | AW64: 0.35233553 | AX64: 0.28508762
B65: Like4like reve growth | C65: 64962506 | D65: 57204481 | E65: 26642112 | F65: 12381605 | G65: 39377330 | H65: 54760930 | I65: 54328857 | J65: 56543769 | K65: 68226943 | L65: 50164385 | M65: 37152307 | N65: 1.8253675e+08 | O65: 21710787 | P65: 21905782 | Q65: 22128555 | R65: 16490710 | S65: 52682089 | T65: 61767078 | U65: 66058237 | V65: 68535637 | W65: 89426845 | X65: 83761899 | Y65: 1.2270635e+08 | Z65: 2.3672892e+08 | AA65: 63061600 | AB65: 56622012 | AC65: 60028677 | AD65: 65340164 | AE65: 64698639 | AF65: 76050187 | AG65: 72534631 | AH65: 82086391 | AI65: 94891809 | AJ65: 90374682 | AK65: 1.3304078e+08 | AL65: 2.6309703e+08 | AM65: 76178048 | AN65: 67482045 | AO65: 68659030 | AP65: 81985947 | AQ65: 77475684 | AR65: 85805412 | AS65: 80970478 | AT65: 90576445 | AU65: 1.050069e+08 | AV65: 1.0791847e+08 | AW65: 1.509434e+08 | AX65: 3.1468105e+08
B66: Pocet uvedenych titulu | C66: 34 | D66: 55 | E66: 53 | F66: 22 | G66: 42 | H66: 38 | I66: 39 | J66: 73 | K66: 88 | L66: 93 | M66: 79 | N66: 33 | O66: 54 | P66: 52 | Q66: 54 | R66: 49 | S66: 69 | T66: 60 | U66: 35 | V66: 70 | W66: 81 | X66: 83 | Y66: 78 | Z66: 49 | AA66: 22 | AB66: 43 | AC66: 51 | AD66: 44 | AE66: 65 | AF66: 61 | AG66: 43 | AH66: 68 | AI66: 65 | AJ66: 76 | AK66: 108 | AL66: 45 | AM66: 42 | AN66: 57 | AO66: 68 | AP66: 64 | AQ66: 73 | AR66: 54 | AS66: 62 | AT66: 71 | AU66: 72 | AV66: 92 | AW66: 72 | AX66: 34
B68: One-off OPEX | AM68: -3.0500671 | AN68: -4.2835654 | AO68: -3.1833175 | AP68: -2.6113995 | AQ68: -2.2483568 | AR68: -3.2062311 | AS68: -2.9057045 | AT68: -2.3793593 | AU68: -2.9858243 | AV68: -8.0805153 | AW68: -4.4395405 | AX68: -5.98498 | AY68: -2.2248 | AZ68: -3.0570248 | BA68: -3.0074379 | BB68: -5.2115612 | BC68: -5.086412 | BD68: -3.067461 | BE68: -8.298921 | BF68: -1.34971 | BG68: -2.520679 | BH68: =1.271317 -> 1.271317 | BI68: =1.473434 -> 1.473434 | BJ68: =-1.493617 -> -1.493617 | BK68: -0.1158723 | BL68: -0.02846522 | BM68: -0.08576634 | BN68: -0.06240866 | BO68: -0.12104445 | BP68: -0.31743236 | BQ68: -0.17191128 | BR68: -0.31674789 | BS68: -2.0609078 | BT68: -1.2840819 | BU68: -4.1183369 | BV68: -5.2466538 | BW68: -5.6250864 | BX68: -6.2722701
B70: Pro-forma EBITDA (EMG + PEMIC) | BE70: -0.11139309 | BF70: 8.3905161 | BG70: 33.436276 | BH70: 23.22297 | BI70: 87.870798 | BJ70: 170.9723 | BK70: 15.007476 | BL70: -2.7741491 | BM70: 0.72859391 | BN70: -3.8806701 | BO70: -4.7220831 | BP70: 6.8343195 | BQ70: 3.5674387 | BR70: 5.3969623 | BS70: 49.829857 | BT70: 43.152239
N71: =N23/23.8 -> 40.840336
AV73: =SUM(AM65:AX65)/SUM(AA65:AL65)-1 -> 0.16567292
B74: -1
B75: 1000000

Sheet EMG_bud
B2: Fiscal/Financial year | C2: =C10 -> 20 | D2: =C10 -> 20 | E2: =C10 -> 20 | F2: =C10 -> 20 | G2: =C10 -> 20 | H2: =C10 -> 20 | I2: =C10 -> 20 | J2: =C10 -> 20 | K2: =C10 -> 20 | L2: =C10 -> 20 | M2: =C10 -> 20 | N2: =C10 -> 20 | O2: =O10 -> 21 | P2: =O10 -> 21 | Q2: =O10 -> 21 | R2: =O10 -> 21 | S2: =O10 -> 21 | T2: =O10 -> 21 | U2: =O10 -> 21 | V2: =O10 -> 21 | W2: =O10 -> 21 | X2: =O10 -> 21 | Y2: =O10 -> 21 | Z2: =O10 -> 21 | AA2: =AA10 -> 22 | AB2: =AA10 -> 22 | AC2: =AA10 -> 22 | AD2: =AA10 -> 22 | AE2: =AA10 -> 22 | AF2: =AA10 -> 22 | AG2: =AA10 -> 22 | AH2: =AA10 -> 22 | AI2: =AA10 -> 22 | AJ2: =AA10 -> 22 | AK2: =AA10 -> 22 | AL2: =AA10 -> 22 | AM2: =AM10 -> 23 | AN2: =AM2 -> 23 | AO2: =AN2 -> 23 | AP2: =AO2 -> 23 | AQ2: =AP2 -> 23 | AR2: =AQ2 -> 23 | AS2: =AR2 -> 23 | AT2: =AS2 -> 23 | AU2: =AT2 -> 23 | ... AX2: =AW2 -> 23 | AY2: =AY10 -> 24 | AZ2: =AY2 -> 24 | BA2: =AZ2 -> 24 | BB2: =BA2 -> 24 | BC2: =BB2 -> 24 | BD2: =BC2 -> 24 | BE2: =BD2 -> 24 | BF2: =BE2 -> 24 | BG2: =BF2 -> 24 | ... BJ2: =BI2 -> 24 | BK2: =BK10 -> 25 | BL2: =BK2 -> 25 | BM2: =BL2 -> 25 | BN2: =BM2 -> 25 | BO2: =BN2 -> 25 | BP2: =BO2 -> 25 | BQ2: =BP2 -> 25 | BR2: =BQ2 -> 25 | BS2: =BR2 -> 25 | ... BV2: =BU2 -> 25 | BW2: =BW10 -> 26 | BX2: =BW2 -> 26 | BY2: =BX2 -> 26 | BZ2: =BY2 -> 26 | CA2: =BZ2 -> 26 | CB2: =CA2 -> 26 | CC2: =CB2 -> 26 | CD2: =CC2 -> 26 | CE2: =CD2 -> 26 | ... CH2: =CG2 -> 26
B3: FY month number | C3: 1 | D3: 2 | E3: 3 | F3: 4 | G3: 5 | H3: 6 | I3: 7 | J3: 8 | K3: 9 | L3: 10 | M3: 11 | N3: 12 | O3: 1 | P3: 2 | Q3: 3 | R3: 4 | S3: 5 | T3: 6 | U3: 7 | V3: 8 | W3: 9 | X3: 10 | Y3: 11 | Z3: 12 | AA3: 1 | AB3: 2 | AC3: 3 | AD3: 4 | AE3: 5 | AF3: 6 | AG3: 7 | AH3: 8 | AI3: 9 | AJ3: 10 | AK3: 11 | AL3: 12 | AM3: 1 | AN3: 2 | AO3: 3 | AP3: 4 | AQ3: 5 | AR3: 6 | AS3: 7 | AT3: 8 | AU3: 9 | AV3: 10 | AW3: 11 | AX3: 12 | AY3: 1 | AZ3: 2 | BA3: 3 | BB3: 4 | BC3: 5 | BD3: 6 | BE3: 7 | BF3: 8 | BG3: 9 | BH3: 10 | BI3: 11 | BJ3: 12 | BK3: 1 | BL3: 2 | BM3: 3 | BN3: 4 | BO3: 5 | BP3: 6 | BQ3: 7 | BR3: 8 | BS3: 9 | BT3: 10 | BU3: 11 | BV3: 12 | BW3: 1 | BX3: 2 | BY3: 3 | BZ3: 4 | CA3: 5 | CB3: 6 | CC3: 7 | CD3: 8 | CE3: 9 | CF3: 10 | CG3: 11 | CH3: 12
B5: Calendar year | C5: 2020 | D5: =IF(C6<D6,C5,C5+1) -> 2020 | E5: =IF(D6<E6,D5,D5+1) -> 2020 | F5: =IF(E6<F6,E5,E5+1) -> 2020 | G5: =IF(F6<G6,F5,F5+1) -> 2020 | H5: =IF(G6<H6,G5,G5+1) -> 2020 | I5: =IF(H6<I6,H5,H5+1) -> 2020 | J5: =IF(I6<J6,I5,I5+1) -> 2020 | K5: =IF(J6<K6,J5,J5+1) -> 2020 | ... CH5: =IF(CG6<CH6,CG5,CG5+1) -> 2026
B6: Calendar month number | C6: =INDEX(EMG!$D$53:$D$64,MATCH(C$3,EMG!$E$53:$E$64,0),1) -> 1 | D6: =INDEX(EMG!$D$53:$D$64,MATCH(D$3,EMG!$E$53:$E$64,0),1) -> 2 | E6: =INDEX(EMG!$D$53:$D$64,MATCH(E$3,EMG!$E$53:$E$64,0),1) -> 3 | F6: =INDEX(EMG!$D$53:$D$64,MATCH(F$3,EMG!$E$53:$E$64,0),1) -> 4 | G6: =INDEX(EMG!$D$53:$D$64,MATCH(G$3,EMG!$E$53:$E$64,0),1) -> 5 | H6: =INDEX(EMG!$D$53:$D$64,MATCH(H$3,EMG!$E$53:$E$64,0),1) -> 6 | I6: =INDEX(EMG!$D$53:$D$64,MATCH(I$3,EMG!$E$53:$E$64,0),1) -> 7 | J6: =INDEX(EMG!$D$53:$D$64,MATCH(J$3,EMG!$E$53:$E$64,0),1) -> 8 | ... CH6: =INDEX(EMG!$D$53:$D$64,MATCH(CH$3,EMG!$E$53:$E$64,0),1) -> 12
B9: BUDGET
C10: =IF(C6=1,C5-2000,C5-2000+1) -> 20 | O10: =IF(O6=1,O5-2000,O5-2000+1) -> 21 | AA10: =IF(AA6=1,AA5-2000,AA5-2000+1) -> 22 | AM10: =IF(AM6=1,AM5-2000,AM5-2000+1) -> 23 | AY10: =IF(AY6=1,AY5-2000,AY5-2000+1) -> 24 | BK10: =IF(BK6=1,BK5-2000,BK5-2000+1) -> 25 | BW10: =IF(BW6=1,BW5-2000,BW5-2000+1) -> 26
B11: CZK million (unless otherwise stated) | C11: =DATE(C5,C6,1) -> 43831 | D11: =DATE(D5,D6,1) -> 43862 | E11: =DATE(E5,E6,1) -> 43891 | F11: =DATE(F5,F6,1) -> 43922 | G11: =DATE(G5,G6,1) -> 43952 | H11: =DATE(H5,H6,1) -> 43983 | I11: =DATE(I5,I6,1) -> 44013 | J11: =DATE(J5,J6,1) -> 44044 | ... CH11: =DATE(CH5,CH6,1) -> 46357
B12: Retail
B13: Distribution
B14: Publishing
B15: Elimination
B16: CONSOLIDATED REVENUES | C16: 0 | D16: 0 | E16: 0 | F16: 0 | G16: 0 | H16: 0 | I16: 0 | J16: 0 | K16: 0 | L16: 0 | M16: 0 | N16: 0 | O16: 0 | P16: 0 | Q16: 0 | R16: 0 | S16: 0 | T16: 0 | U16: 0 | V16: 0 | W16: 0 | X16: 0 | Y16: 0 | Z16: 0 | AA16: 122 | AB16: 94 | AC16: 249 | AD16: 153 | AE16: 37 | AF16: 151 | AG16: 267 | AH16: 232 | AI16: 237 | AJ16: 188 | AK16: 17 | AL16: 209 | AM16: 300 | AN16: 147 | AO16: 88 | AP16: 48 | AQ16: 138 | AR16: 268 | AS16: 159 | AT16: 64 | AU16: 66 | AV16: 32 | AW16: 231 | AX16: 107 | AY16: 54 | AZ16: 1 | BA16: 7 | BB16: 124 | BC16: 149 | BD16: 67 | BE16: 277 | BF16: 19 | BG16: 52 | BH16: 116 | BI16: 2 | BJ16: 190 | BK16: 185 | BL16: 74 | BM16: 102 | BN16: 188 | BO16: 216 | BP16: 93 | BQ16: 206 | BR16: 106 | BS16: 179 | BT16: 55 | BU16: 269 | BV16: 117 | BW16: 12 | BX16: 86 | BY16: 238.67256 | BZ16: 233.67251 | CA16: 249.81408 | CB16: 262.46088 | CC16: 262.79664 | CD16: 296.15092 | CE16: 367.16468 | CF16: 363.6385 | CG16: 488.94554 | CH16: 842.29582
B17: Gross Margin | C17: 7 | D17: 22 | E17: 31 | F17: 64 | G17: 98 | H17: 70 | I17: 34 | J17: 30 | K17: 41 | L17: 11 | M17: 100 | N17: 81 | O17: 63 | P17: 92 | Q17: 28 | R17: 50 | S17: 70 | T17: 98 | U17: 66 | V17: 35 | W17: 51 | X17: 5 | Y17: 7 | Z17: 7 | AA17: 16 | AB17: 43 | AC17: 81 | AD17: 39 | AE17: 62 | AF17: 98 | AG17: 81 | AH17: 69 | AI17: 41 | AJ17: 34 | AK17: 67 | AL17: 69 | AM17: 38 | AN17: 99 | AO17: 80 | AP17: 60 | AQ17: 54 | AR17: 74 | AS17: 16 | AT17: 42 | AU17: 92 | AV17: 21 | AW17: 39 | AX17: 10 | AY17: 11 | AZ17: 79 | BA17: 25 | BB17: 75 | BC17: 59 | BD17: 47 | BE17: 91 | BF17: 23 | BG17: 58 | BH17: 17 | BI17: 25 | BJ17: 23 | BK17: 96 | BL17: 75 | BM17: 91 | BN17: 97 | BO17: 94 | BP17: 65 | BQ17: 44 | BR17: 52 | BS17: 47 | BT17: 24 | BU17: 93 | BV17: 26 | BW17: 45 | BX17: 17 | BY17: 86.280749 | BZ17: 90.847822 | CA17: 99.116993 | CB17: 100.61902 | CC17: 102.3538 | CD17: 116.32665 | CE17: 135.91275 | CF17: 138.22573 | CG17: 182.42971 | CH17: 340.80166
B18: % of Revenues | C18: #DIV/0! | D18: #DIV/0! | E18: #DIV/0! | F18: #DIV/0! | G18: #DIV/0! | H18: #DIV/0! | I18: #DIV/0! | J18: #DIV/0! | K18: #DIV/0! | L18: #DIV/0! | M18: #DIV/0! | N18: #DIV/0! | O18: #DIV/0! | P18: #DIV/0! | Q18: #DIV/0! | R18: #DIV/0! | S18: #DIV/0! | T18: #DIV/0! | U18: #DIV/0! | V18: #DIV/0! | W18: #DIV/0! | X18: #DIV/0! | Y18: #DIV/0! | Z18: #DIV/0! | AA18: 0.13114754 | AB18: 0.45744681 | AC18: 0.3253012 | AD18: 0.25490196 | AE18: 1.6756757 | AF18: 0.64900662 | AG18: 0.30337079 | AH18: 0.29741379 | AI18: 0.17299578 | AJ18: 0.18085106 | AK18: 3.9411765 | AL18: 0.33014354 | AM18: 0.12666667 | AN18: 0.67346939 | AO18: 0.90909091 | AP18: 1.25 | AQ18: 0.39130435 | AR18: 0.2761194 | AS18: 0.10062893 | AT18: 0.65625 | AU18: 1.3939394 | AV18: 0.65625 | AW18: 0.16883117 | AX18: 0.093457944 | AY18: 0.2037037 | AZ18: 79 | BA18: 3.5714286 | BB18: 0.60483871 | BC18: 0.39597315 | BD18: 0.70149254 | BE18: 0.32851986 | BF18: 1.2105263 | BG18: 1.1153846 | BH18: 0.14655172 | BI18: 12.5 | BJ18: 0.12105263 | BK18: 0.37449263 | BL18: 0.36167017 | BM18: 0.36721414 | BN18: 0.3598879 | BO18: 0.37950756 | BP18: 0.38628966 | BQ18: 0.37891805 | BR18: 0.36598393 | BS18: 0.35850634 | BT18: 0.36980752 | BU18: 0.36046538 | BV18: 0.39657846 | BW18: 0.35374369 | BX18: 0.36701163 | BY18: =BY17/BY$16 -> 0.36150259 | BZ18: =BZ17/BZ$16 -> 0.38878267 | CA18: =CA17/CA$16 -> 0.39676304 | CB18: =CB17/CB$16 -> 0.3833677 | CC18: =CC17/CC$16 -> 0.3894791 | CD18: =CD17/CD$16 -> 0.39279516 | CE18: =CE17/CE$16 -> 0.37016835 | CF18: =CF17/CF$16 -> 0.38011853 | ... CH18: =CH17/CH$16 -> 0.40461042
B19: REP. EBITDA (Excl. Licence Depreciation) | C19: 7 | D19: 6 | E19: 37 | F19: 45 | G19: 28 | H19: 16 | I19: 17 | J19: 35 | K19: 16 | L19: 12 | M19: 10 | N19: 21 | O19: 12 | P19: 8 | Q19: 3 | R19: 19 | S19: 27 | T19: 42 | U19: 49 | V19: 36 | W19: 3 | X19: 19 | Y19: 32 | Z19: 37 | AA19: 34 | AB19: 41 | AC19: 45 | AD19: 38 | AE19: 23 | AF19: 8 | AG19: 21 | AH19: 28 | AI19: 39 | AJ19: 35 | AK19: 18 | AL19: 38 | AM19: 39 | AN19: 32 | AO19: 19 | AP19: 44 | AQ19: 7 | AR19: 25 | AS19: 1 | AT19: 38 | AU19: 45 | AV19: 21 | AW19: 7 | AX19: 35 | AY19: 4 | AZ19: 4 | BA19: 10 | BB19: 45 | BC19: 18 | BD19: 34 | BE19: 47 | BF19: 22 | BG19: 20 | BH19: 49 | BI19: 21 | BJ19: 1 | BK19: 37 | BL19: 3 | BM19: 21 | BN19: 47 | BO19: 46 | BP19: 27 | BQ19: 0 | BR19: 47 | BS19: 4 | BT19: 38 | BU19: 40 | BV19: 2 | BW19: 19 | BX19: 41 | BY19: -9.065337 | BZ19: 3.6284588 | CA19: 9.5785192 | CB19: 12.333321 | CC19: 8.7388397 | CD19: 27.809398 | CE19: 39.419515 | CF19: 42.414286 | CG19: 74.804309 | CH19: 186.54848
B20: % of Revenues | C20: #DIV/0! | D20: #DIV/0! | E20: #DIV/0! | F20: #DIV/0! | G20: #DIV/0! | H20: #DIV/0! | I20: #DIV/0! | J20: #DIV/0! | K20: #DIV/0! | L20: #DIV/0! | M20: #DIV/0! | N20: #DIV/0! | O20: #DIV/0! | P20: #DIV/0! | Q20: #DIV/0! | R20: #DIV/0! | S20: #DIV/0! | T20: #DIV/0! | U20: #DIV/0! | V20: #DIV/0! | W20: #DIV/0! | X20: #DIV/0! | Y20: #DIV/0! | Z20: #DIV/0! | AA20: 0.27868852 | AB20: 0.43617021 | AC20: 0.18072289 | AD20: 0.24836601 | AE20: 0.62162162 | AF20: 0.052980132 | AG20: 0.078651685 | AH20: 0.12068966 | AI20: 0.16455696 | AJ20: 0.18617021 | AK20: 1.0588235 | AL20: 0.18181818 | AM20: 0.13 | AN20: 0.21768707 | AO20: 0.21590909 | AP20: 0.91666667 | AQ20: 0.050724638 | AR20: 0.093283582 | AS20: 0.0062893082 | AT20: 0.59375 | AU20: 0.68181818 | AV20: 0.65625 | AW20: 0.03030303 | AX20: 0.3271028 | AY20: 0.074074074 | AZ20: 4 | BA20: 1.4285714 | BB20: 0.36290323 | BC20: 0.12080537 | BD20: 0.50746269 | BE20: 0.16967509 | BF20: 1.1578947 | BG20: 0.38461538 | BH20: 0.42241379 | BI20: 10.5 | BJ20: 0.0052631579 | BK20: 0.051978575 | BL20: -0.012041004 | BM20: 0.0025599612 | BN20: -0.016940532 | BO20: -0.020035975 | BP20: 0.025115864 | BQ20: 0.014414341 | BR20: 0.019856508 | BS20: 0.12269235 | BT20: 0.11640395 | BU20: 0.12455088 | BV20: 0.21303006 | BW20: 0.001512005 | BX20: -0.0077679233 | BY20: =BY19/BY$16 -> -0.037982318 | BZ20: =BZ19/BZ$16 -> 0.015527966 | CA20: =CA19/CA$16 -> 0.038342592 | CB20: =CB19/CB$16 -> 0.046991082 | CC20: =CC19/CC$16 -> 0.033253239 | CD20: =CD19/CD$16 -> 0.093902791 | CE20: =CE19/CE$16 -> 0.10736195 | CF20: =CF19/CF$16 -> 0.1166386 | ... CH20: =CH19/CH$16 -> 0.22147621
B21: CAPEX | C21: 12 | D21: 11 | E21: 7 | F21: 4 | G21: 16 | H21: 2 | I21: 5 | J21: 0 | K21: 2 | L21: 10 | M21: 19 | N21: 5 | O21: 3 | P21: 9 | Q21: 18 | R21: 11 | S21: 18 | T21: 0 | U21: 5 | V21: 5 | W21: 5 | X21: 18 | Y21: 12 | Z21: 13 | AA21: 3 | AB21: 6 | AC21: 0 | AD21: 4 | AE21: 7 | AF21: 20 | AG21: 12 | AH21: 7 | AI21: 11 | AJ21: 6 | AK21: 17 | AL21: 3 | AM21: 7 | AN21: 18 | AO21: 6 | AP21: 9 | AQ21: 16 | AR21: 18 | AS21: 18 | AT21: 13 | AU21: 1 | AV21: 10 | AW21: 18 | AX21: 17 | AY21: 16 | AZ21: 10 | BA21: 13 | BB21: 12 | BC21: 6 | BD21: 2 | BE21: 1 | BF21: 14 | BG21: 10 | BH21: 12 | BI21: 19 | BJ21: 15 | BK21: 6 | BL21: 3 | BM21: 19 | BN21: 4 | BO21: 2 | BP21: 13 | BQ21: 1 | BR21: 12 | BS21: 12 | BT21: 17 | BU21: 16 | BV21: 3 | BW21: 10 | BX21: 9 | BY21: -30.745796 | BZ21: -12.86712 | CA21: -12.269939 | CB21: -21.273809 | CC21: -8.4346523 | CD21: -7.3591225 | CE21: -7.6211739 | CF21: -8.5656801 | CG21: -8.0188526 | CH21: -7.0965099
B22: NET DEBT | C22: 921 | D22: 910 | E22: 874 | F22: 920 | G22: 957 | H22: 906 | I22: 915 | J22: 955 | K22: 924 | L22: 967 | M22: 964 | N22: 874 | O22: 909 | P22: 875 | Q22: 947 | R22: 947 | S22: 962 | T22: 891 | U22: 900 | V22: 886 | W22: 954 | X22: 874 | Y22: 888 | Z22: 895 | AA22: 902 | AB22: 893 | AC22: 962 | AD22: 944 | AE22: 924 | AF22: 916 | AG22: 957 | AH22: 916 | AI22: 926 | AJ22: 944 | AK22: 878 | AL22: 961 | AM22: 888 | AN22: 927 | AO22: 937 | AP22: 895 | AQ22: 941 | AR22: 959 | AS22: 891 | AT22: 901 | AU22: 921 | AV22: 875 | AW22: 942 | AX22: 942 | AY22: 956 | AZ22: 895 | BA22: 933 | BB22: 876 | BC22: 884 | BD22: 925 | BE22: 913 | BF22: 943 | BG22: 915 | BH22: 934 | BI22: 883 | BJ22: 957 | BK22: 965 | BL22: 928 | BM22: 965 | BN22: 968 | BO22: 918 | BP22: 933 | BQ22: 914 | BR22: 940 | BS22: 962 | BT22: 950 | BU22: 945 | BV22: 959 | BW22: 970 | BX22: 893 | BY22: =BY23-BY24 -> 1310.8842 | BZ22: =BZ23-BZ24 -> 1351.532 | CA22: =CA23-CA24 -> 1397.2632 | CB22: =CB23-CB24 -> 1401.7795 | CC22: =CC23-CC24 -> 1411.593 | CD22: =CD23-CD24 -> 1415.1972 | CE22: =CE23-CE24 -> 1386.6752 | CF22: =CF23-CF24 -> 1359.4494 | ... CH22: =CH23-CH24 -> 841.92626
B23: Debt | C23: 972 | D23: 972 | E23: 972 | F23: 972 | G23: 972 | H23: 972 | I23: 972 | J23: 972 | K23: 972 | L23: 972 | M23: 972 | N23: 972 | O23: 972 | P23: 972 | Q23: 972 | R23: 972 | S23: 972 | T23: 972 | U23: 972 | V23: 972 | W23: 972 | X23: 972 | Y23: 972 | Z23: 972 | AA23: 972 | AB23: 972 | AC23: 972 | AD23: 972 | AE23: 972 | AF23: 972 | AG23: 972 | AH23: 972 | AI23: 972 | AJ23: 972 | AK23: 972 | AL23: 972 | AM23: 972 | AN23: 972 | AO23: 972 | AP23: 972 | AQ23: 972 | AR23: 972 | AS23: 972 | AT23: 972 | AU23: 972 | AV23: 972 | AW23: 972 | AX23: 972 | AY23: 972 | AZ23: 972 | BA23: 972 | BB23: 972 | BC23: 972 | BD23: 972 | BE23: 972 | BF23: 972 | BG23: 972 | BH23: 972 | BI23: 972 | BJ23: 972 | BK23: 972 | BL23: 972 | BM23: 972 | BN23: 972 | BO23: 972 | BP23: 972 | BQ23: 972 | BR23: 972 | BS23: 972 | BT23: 972 | BU23: 972 | BV23: 972 | BW23: 972 | BX23: 972 | BY23: 1324.1974 | BZ23: 1364.1974 | CA23: 1414.1974 | CB23: 1419.6382 | CC23: 1429.6382 | CD23: 1429.6382 | CE23: 1409.6382 | CF23: 1389.6382 | CG23: 1364.6382 | CH23: 905.96053
B24: Cash | C24: 51 | D24: 62 | E24: 98 | F24: 52 | G24: 15 | H24: 66 | I24: 57 | J24: 17 | K24: 48 | L24: 5 | M24: 8 | N24: 98 | O24: 63 | P24: 97 | Q24: 25 | R24: 25 | S24: 10 | T24: 81 | U24: 72 | V24: 86 | W24: 18 | X24: 98 | Y24: 84 | Z24: 77 | AA24: 70 | AB24: 79 | AC24: 10 | AD24: 28 | AE24: 48 | AF24: 56 | AG24: 15 | AH24: 56 | AI24: 46 | AJ24: 28 | AK24: 94 | AL24: 11 | AM24: 84 | AN24: 45 | AO24: 35 | AP24: 77 | AQ24: 31 | AR24: 13 | AS24: 81 | AT24: 71 | AU24: 51 | AV24: 97 | AW24: 30 | AX24: 30 | AY24: 16 | AZ24: 77 | BA24: 39 | BB24: 96 | BC24: 88 | BD24: 47 | BE24: 59 | BF24: 29 | BG24: 57 | BH24: 38 | BI24: 89 | BJ24: 15 | BK24: 7 | BL24: 44 | BM24: 7 | BN24: 4 | BO24: 54 | BP24: 39 | BQ24: 58 | BR24: 32 | BS24: 10 | BT24: 22 | BU24: 27 | BV24: 13 | BW24: 2 | BX24: 79 | BY24: 13.313167 | BZ24: 12.665354 | CA24: 16.93419 | CB24: 17.858698 | CC24: 18.045152 | CD24: 14.441007 | CE24: 22.963002 | CF24: 30.188723 | CG24: 30.202025 | CH24: 64.034262
B25: Net Debt / LTM EBITDA | O25: 3.5647059 | P25: 3.4046693 | Q25: 4.2466368 | R25: 4.8071066 | S25: 4.9081633 | T25: 4.0135135 | U25: 3.5433071 | V25: 3.4745098 | W25: 3.9421488 | X25: 3.5100402 | Y25: 3.2767528 | Z25: 3.1184669 | AA25: 2.9190939 | AB25: 2.6111111 | AC25: 2.5052083 | AD25: 2.3424318 | AE25: 2.3157895 | AF25: 2.509589 | AG25: 2.8397626 | AH25: 2.7841945 | AI25: 2.5369863 | AJ25: 2.4776903 | AK25: 2.3923706 | AL25: 2.611413 | AM25: 2.6571838 | AN25: 3.1780362 | AO25: 3.9056928 | AP25: 4.3562408 | AQ25: 5.3535449 | AR25: 5.7310627 | AS25: 6.3921174 | AT25: 7.6875169 | AU25: 10.101486 | AV25: 11.420379 | AW25: 8.7525127 | AX25: 4.6911393 | AY25: 4.6219188 | AZ25: 4.1551306 | BA25: 3.9670537 | BB25: 3.1080081 | BC25: 2.8367889 | BD25: 2.6494802 | BE25: 2.2194278 | BF25: 2.198625 | BG25: 2.0868809 | BH25: 2.0054135 | BI25: 2.0240357 | BJ25: 3.1114578 | BK25: 2.8511161 | BL25: 2.774826 | BM25: 2.8174054 | BN25: 2.8523898 | BO25: 2.5331182 | BP25: 2.7852828 | BQ25: 2.6989215 | BR25: 2.8004509 | BS25: 2.7325368 | BT25: 2.5538796 | BU25: 2.9423066 | BV25: 2.9423529 | BW25: 3.3540635 | BX25: 3.1409482 | BY25: 4.6795006 | BZ25: 4.7708838 | CA25: 4.6939232 | CB25: 4.6610751 | CC25: 4.534365 | CD25: 4.316727 | CE25: 4.1498144 | CF25: 3.815226 | CG25: 3.6965548 | CH25: 2.0759068
B28: EBITDA for leverage | C28: {=_xlfn.IFS(EMG!$I$6=(C$2+2000),C29,(C$2+2000)<EMG!$I$6,EMG_act!C$29)} -> 7 | D28: {=_xlfn.IFS(EMG!$I$6=(D$2+2000),D29,(D$2+2000)<EMG!$I$6,EMG_act!D$29)} -> 6 | E28: {=_xlfn.IFS(EMG!$I$6=(E$2+2000),E29,(E$2+2000)<EMG!$I$6,EMG_act!E$29)} -> 37 | F28: {=_xlfn.IFS(EMG!$I$6=(F$2+2000),F29,(F$2+2000)<EMG!$I$6,EMG_act!F$29)} -> 45 | G28: {=_xlfn.IFS(EMG!$I$6=(G$2+2000),G29,(G$2+2000)<EMG!$I$6,EMG_act!G$29)} -> 28 | H28: {=_xlfn.IFS(EMG!$I$6=(H$2+2000),H29,(H$2+2000)<EMG!$I$6,EMG_act!H$29)} -> 16 | I28: {=_xlfn.IFS(EMG!$I$6=(I$2+2000),I29,(I$2+2000)<EMG!$I$6,EMG_act!I$29)} -> 17 | J28: {=_xlfn.IFS(EMG!$I$6=(J$2+2000),J29,(J$2+2000)<EMG!$I$6,EMG_act!J$29)} -> 35 | ... CH28: {=_xlfn.IFS(EMG!$I$6=(CH$2+2000),CH29,(CH$2+2000)<EMG!$I$6,EMG_act!CH$29)} -> 186.54848
B29: Adjusted EBITDA BUDGET | C29: =C19-C68 -> 7 | D29: =D19-D68 -> 6 | E29: =E19-E68 -> 37 | F29: =F19-F68 -> 45 | G29: =G19-G68 -> 28 | H29: =H19-H68 -> 16 | I29: =I19-I68 -> 17 | J29: =J19-J68 -> 35 | ... CH29: =CH19-CH68 -> 186.54848
B33: Net debt
B34: Luxor - Bank loans and borrowings | C34: 0 | D34: 0 | E34: 0 | F34: 0 | G34: 0 | H34: 0 | I34: 0 | J34: 0 | K34: 0 | L34: 0 | M34: 0 | N34: 0 | O34: 0 | P34: 0 | Q34: 0 | R34: 0 | S34: 0 | T34: 0 | U34: 0 | V34: 0 | W34: 0 | X34: 0 | Y34: 0 | Z34: 0 | AA34: 0 | AB34: 0 | AC34: 0 | AD34: 0 | AE34: 0 | AF34: 0 | AG34: 0 | AH34: 0 | AI34: 0 | AJ34: 0 | AK34: 0 | AL34: 0
B35: Luxor - Short-term Bank loans and borrowings | C35: 0 | D35: 0 | E35: 0 | F35: 0 | G35: 0 | H35: 0 | I35: 0 | J35: 0 | K35: 0 | L35: 0 | M35: 0 | N35: 0 | O35: 49.867642 | P35: 49.867642 | Q35: 49.867642 | R35: 49.867642 | S35: 49.867642 | T35: 49.867642 | U35: 49.867642 | V35: 49.867642 | W35: 49.867642 | X35: 49.867642 | Y35: 49.867642 | Z35: 49.867642 | AA35: 0 | AB35: 0 | AC35: 0 | AD35: 0 | AE35: 0 | AF35: 0 | AG35: 0 | AH35: 0 | AI35: 0 | AJ35: 0 | AK35: 0 | AL35: 0
B36: EMG - Bank loans and borrowings | C36: 280.84279 | D36: 280.84279 | E36: 282.45986 | F36: 282.45986 | G36: 282.45986 | H36: 276.54042 | I36: 276.54042 | J36: 276.54042 | K36: 268.89086 | L36: 268.89086 | M36: 268.89086 | N36: 205.34392 | O36: 209.46826 | P36: 209.46826 | Q36: 201.8187 | R36: 201.8187 | S36: 201.8187 | T36: 194.16914 | U36: 194.16914 | V36: 194.16914 | W36: 186.51958 | X36: 186.51958 | Y36: 186.51958 | Z36: 127.97264 | AA36: 0 | AB36: 0 | AC36: 0 | AD36: 0 | AE36: 0 | AF36: 0 | AG36: 0 | AH36: 0 | AI36: 0 | AJ36: 0 | AK36: 0 | AL36: 0
B37: EMG - Short-term Bank loans and borrowings RCF | C37: 172.54054 | D37: 188.11036 | E37: 172.54082 | F37: 174.34665 | G37: 175.25781 | H37: 180.28897 | I37: 181.12024 | J37: 181.94665 | K37: 186.9902 | L37: 187.81123 | M37: 188.59955 | N37: 133.5988 | O37: 87.569257 | P37: 128.71406 | Q37: 181.118 | R37: 229.9 | S37: 229.9 | T37: 229.9 | U37: 229.9 | V37: 229.9 | W37: 229.9 | X37: 169.9 | Y37: 109.9 | Z37: 49.9 | AA37: 0 | AB37: 0 | AC37: 0 | AD37: 0 | AE37: 0 | AF37: 0 | AG37: 0 | AH37: 0 | AI37: 0 | AJ37: 0 | AK37: 0 | AL37: 0
B38: EMG - Short-term part of Long term Bank loans | C38: 81.496 | D38: 81.496 | E38: 81.496 | F38: 81.496 | G38: 81.496 | H38: 81.496 | I38: 81.496 | J38: 81.496 | K38: 81.496 | L38: 81.496 | M38: 81.496 | N38: 81.496 | O38: 81.496 | P38: 81.496 | Q38: 81.496 | R38: 81.496 | S38: 81.496 | T38: 81.496 | U38: 81.496 | V38: 81.496 | W38: 81.496 | X38: 81.496 | Y38: 81.496 | Z38: 81.496 | AA38: 0 | AB38: 0 | AC38: 0 | AD38: 0 | AE38: 0 | AF38: 0 | AG38: 0 | AH38: 0 | AI38: 0 | AJ38: 0 | AK38: 0 | AL38: 0
B39: Other debt 1 | C39: 250 | D39: 250 | E39: 250 | F39: 250 | G39: 250 | H39: 250 | I39: 250 | J39: 250 | K39: 250 | L39: 250 | M39: 250 | N39: 250 | O39: 250 | P39: 250 | Q39: 250 | R39: 250 | S39: 250 | T39: 250 | U39: 250 | V39: 250 | W39: 250 | X39: 250 | Y39: 250 | Z39: 250 | AA39: 250 | AB39: 250 | AC39: 250 | AD39: 250 | AE39: 250 | AF39: 250 | AG39: 250 | AH39: 250 | AI39: 250 | AJ39: 250 | AK39: 250 | AL39: 250
B40: Other debt 2 | C40: 52.5 | D40: 52.5 | E40: 52.5 | F40: 52.5 | G40: 52.5 | H40: 52.5 | I40: 52.5 | J40: 52.5 | K40: 52.5 | L40: 52.5 | M40: 52.5 | N40: 52.5 | O40: 52.5 | P40: 52.5 | Q40: 52.5 | R40: 52.5 | S40: 52.5 | T40: 52.5 | U40: 52.5 | V40: 52.5 | W40: 52.5 | X40: 52.5 | Y40: 52.5 | Z40: 52.5 | AA40: 52.5 | AB40: 52.5 | AC40: 52.5 | AD40: 52.5 | AE40: 52.5 | AF40: 52.5 | AG40: 52.5 | AH40: 52.5 | AI40: 52.5 | AJ40: 52.5 | AK40: 52.5 | AL40: 52.5
B41: Cash - EMG | C41: -2.868183 | D41: -1.9863696 | E41: -2.1567572 | F41: -0.9999 | G41: -1 | H41: -0.9999 | I41: -0.9998 | J41: -0.9997 | K41: -0.9996 | L41: -0.9999 | M41: -0.9999 | N41: -1.0004995 | O41: -2.0818162 | P41: -51.963524 | Q41: -52.097251 | R41: -31.983422 | S41: -21.529601 | T41: -22.831649 | U41: -11.585288 | V41: -7.421462 | W41: -13.664233 | X41: -14.044673 | Y41: -16.624303 | Z41: -32.090747 | AA41: 0 | AB41: 0 | AC41: 0 | AD41: 0 | AE41: 0 | AF41: 0 | AG41: 0 | AH41: 0 | AI41: 0 | AJ41: 0 | AK41: 0 | AL41: 0
B42: Cash - Luxor | C42: -10.177826 | D42: -9.7954163 | E42: -15.311255 | F42: -19.20972 | G42: -17.95906 | H42: -10.170041 | I42: -8.1384732 | J42: -8.2076872 | K42: -10.699321 | L42: -6.8727231 | M42: -7.3624502 | N42: -23.13905 | O42: -25.249083 | P42: -11.139516 | Q42: -8.9529182 | R42: -9.4028925 | S42: -16.32349 | T42: -15.088723 | U42: -14.624276 | V42: -17.185287 | W42: -16.628863 | X42: -13.635261 | Y42: -14.872389 | Z42: -31.761915 | AA42: 0 | AB42: 0 | AC42: 0 | AD42: 0 | AE42: 0 | AF42: 0 | AG42: 0 | AH42: 0 | AI42: 0 | AJ42: 0 | AK42: 0 | AL42: 0
B43: TOTAL | C43: 824.33332 | D43: 841.16736 | E43: 821.52867 | F43: 820.59289 | G43: 822.75461 | H43: 829.65545 | I43: 832.51839 | J43: 833.27569 | K43: 828.17814 | L43: 832.82547 | M43: 833.12406 | N43: 698.79918 | O43: 703.57026 | P43: 708.94292 | Q43: 755.75018 | R43: 824.19603 | S43: 827.72925 | T43: 820.01241 | U43: 831.72322 | V43: 833.32603 | W43: 819.99012 | X43: 762.60329 | Y43: 698.78653 | Z43: 547.88362 | AA43: 302.5 | AB43: 302.5 | AC43: 302.5 | AD43: 302.5 | AE43: 302.5 | AF43: 302.5 | AG43: 302.5 | AH43: 302.5 | AI43: 302.5 | AJ43: 302.5 | AK43: 302.5 | AL43: 302.5
B50: in thousands EUR
B52: EMG GM | C52: 34797.902 | D52: 34068.725 | E52: 20343.815 | F52: 14593.993 | G52: 22640.948 | H52: 29779.708 | I52: 29330.231 | J52: 33642.008 | K52: 46705.853 | L52: 49195.432 | M52: 81841.934 | N52: 125180.29 | O52: 32282.766 | P52: 32680.857 | Q52: 23738.49 | R52: 31143.529 | S52: 37556.852 | T52: 44400.135 | U52: 37194.225 | V52: 40568.837 | W52: 54535.014 | X52: 52147.934 | Y52: 86696.292 | Z52: 123117.42 | AA52: 34797.902 | AB52: 34068.725 | AC52: 20343.815 | AD52: 14593.993 | AE52: 22640.948 | AF52: 29779.708 | AG52: 29330.231 | AH52: 33642.008 | AI52: 46705.853 | AJ52: 49195.432 | AK52: 81841.934 | AL52: 125180.29
B53: NLX GM | C53: 23586.605 | D53: 19517.574 | E53: 10117.865 | F53: 2374.3722 | G53: 8783.2427 | H53: 15892.971 | I53: 19384.979 | J53: 21555.141 | K53: 27475.716 | L53: 28165.829 | M53: 39858.623 | N53: 85590.765 | O53: 7356.6663 | P53: 4382.7045 | Q53: 20731.274 | R53: 5060.7422 | S53: 19712.523 | T53: 18920.438 | U53: 20565.558 | V53: 24682.486 | W53: 33469.944 | X53: 31438.666 | Y53: 50782.519 | Z53: 95622.567 | AA53: 23586.605 | AB53: 19517.574 | AC53: 10117.865 | AD53: 2374.3722 | AE53: 8783.2427 | AF53: 15892.971 | AG53: 19384.979 | AH53: 21555.141 | AI53: 27475.716 | AJ53: 28165.829 | AK53: 39858.623 | AL53: 85590.765
B54: TOTAL | C54: 58384.507 | D54: 53586.299 | E54: 30461.68 | F54: 16968.365 | G54: 31424.19 | H54: 45672.68 | I54: 48715.21 | J54: 55197.149 | K54: 74181.568 | L54: 77361.261 | M54: 121700.56 | N54: 210771.05 | O54: 39639.432 | P54: 37063.562 | Q54: 44469.763 | R54: 36204.271 | S54: 57269.375 | T54: 63320.572 | U54: 57759.783 | V54: 65251.323 | W54: 88004.958 | X54: 83586.6 | Y54: 137478.81 | Z54: 218739.99 | AA54: 58384.507 | AB54: 53586.299 | AC54: 30461.68 | AD54: 16968.365 | AE54: 31424.19 | AF54: 45672.68 | AG54: 48715.21 | AH54: 55197.149 | AI54: 74181.568 | AJ54: 77361.261 | AK54: 121700.56 | AL54: 210771.05
B57: EMG EBITDA | C57: 1121.2885 | D57: 1825.9179 | E57: 316.88614 | F57: -2495.1928 | G57: -1361.6069 | H57: 4214.4068 | I57: 5713.9323 | J57: 2752.6528 | K57: 10799.107 | L57: 10104.837 | M57: 35011.79 | N57: 75365.745 | O57: 6561.0756 | P57: 6756.7721 | Q57: -4331.876 | R57: 6117.7122 | S57: 8466.5085 | T57: 12579.184 | U57: 10511.554 | V57: 9564.8727 | W57: 19393.724 | X57: 13772.488 | Y57: 42583.15 | Z57: 52175.2 | AA57: 1121.2885 | AB57: 1825.9179 | AC57: 316.88614 | AD57: -2495.1928 | AE57: -1361.6069 | AF57: 4214.4068 | AG57: 5713.9323 | AH57: 2752.6528 | AI57: 10799.107 | AJ57: 10104.837 | AK57: 35011.79 | AL57: 75365.745
B58: NLX EBITDA | C58: -2570.0922 | D58: -2305.6041 | E58: -26267.35 | F58: -15570.848 | G58: -596.39076 | H58: -11823.019 | I58: -8792.5833 | J58: -6703.8638 | K58: -1700.2471 | L58: 269.14161 | M58: 12289.955 | N58: 39082.177 | O58: -17410.095 | P58: -20471.602 | Q58: -8636.4012 | R58: -19429.177 | S58: -9919.9209 | T58: -10335.003 | U58: -7969.9552 | V58: -5987.7854 | W58: 975.2424 | X58: 2789.8342 | Y58: 22184.67 | Z58: 54607.689 | AA58: -2570.0922 | AB58: -2305.6041 | AC58: -26267.35 | AD58: -15570.848 | AE58: -596.39076 | AF58: -11823.019 | AG58: -8792.5833 | AH58: -6703.8638 | AI58: -1700.2471 | AJ58: 269.14161 | AK58: 12289.955 | AL58: 39082.177
B59: TOTAL | C59: -1448.8037 | D59: -479.68613 | E59: -25950.464 | F59: -18066.041 | G59: -1957.9977 | H59: -7608.6121 | I59: -3078.651 | J59: -3951.211 | K59: 9098.8602 | L59: 10373.979 | M59: 47301.745 | N59: 114447.92 | O59: -10849.019 | P59: -13714.83 | Q59: -12968.277 | R59: -13311.465 | S59: -1453.4125 | T59: 2244.181 | U59: 2541.5989 | V59: 3577.0873 | W59: 20368.967 | X59: 16562.322 | Y59: 64767.82 | Z59: 106782.89 | AA59: -1448.8037 | AB59: -479.68613 | AC59: -25950.464 | AD59: -18066.041 | AE59: -1957.9977 | AF59: -7608.6121 | AG59: -3078.651 | AH59: -3951.211 | AI59: 9098.8602 | AJ59: 10373.979 | AK59: 47301.745 | AL59: 114447.92
B60: B2C revenues total (NLX, KK, BT) | AA60: 100.85324 | AB60: 89.292891 | AC60: 123.24982 | AD60: 106.49316 | AE60: 117.79158 | AF60: 125.8206 | AG60: 120.18298 | AH60: 131.80975 | AI60: 195.28308 | AJ60: 153.09346 | AK60: 277.48209 | AL60: 394.37171 | AM60: 112.97648 | AN60: 107.69804 | AO60: 110.1848 | AP60: 116.84866 | AQ60: 108.01942 | AR60: 136.61772 | AS60: 114.76647 | AT60: 132.89612 | AU60: 163.59496 | AV60: 145.52289 | AW60: 260.52068 | AX60: 402.66946
B61: On-line revenues (KK on-line, BT, NLX on-line včetně BOPS) | AA61: 32.168685 | AB61: 29.217014 | AC61: 42.08866 | AD61: 33.497443 | AE61: 39.137347 | AF61: 42.82364 | AG61: 37.626164 | AH61: 41.824946 | AI61: 75.507361 | AJ61: 52.382407 | AK61: 124.23933 | AL61: 98.213136 | AM61: 36.980008 | AN61: 36.131731 | AO61: 33.227699 | AP61: 35.130833 | AQ61: 32.250503 | AR61: 38.927122 | AS61: 32.020033 | AT61: 41.94946 | AU61: 60.271201 | AV61: 48.071913 | AW61: 99.890713 | AX61: 114.42514
B64: Share of online | AA64: =AA61/AA60 -> 0.31896532 | AB64: =AB61/AB60 -> 0.32720426 | AC64: =AC61/AC60 -> 0.34149065 | AD64: =AD61/AD60 -> 0.31455018 | AE64: =AE61/AE60 -> 0.33225929 | AF64: =AF61/AF60 -> 0.34035475 | AG64: =AG61/AG60 -> 0.31307398 | AH64: =AH61/AH60 -> 0.317313 | ... AX64: =AX61/AX60 -> 0.28416642
B65: Revenue per m2 (nebo like for like growth)
B66: Pocet uvedenych titulu | AL66: 871 | AX66: 878
B68: One-off OPEX | AM68: -1.8036739 | AN68: -4.1539739 | AO68: -1.7990699 | AP68: -2.2862239 | AQ68: -1.6814739 | AR68: -2.7774739 | AS68: -4.0505239 | AT68: -5.4605409 | AU68: -3.2034739 | AV68: -5.4259739 | AW68: -2.8094739 | AX68: -2.8049739 | AY68: -2.607276 | AZ68: -7.521885 | BA68: -3.393895 | BB68: -3.101896 | BC68: -1.8657944 | BD68: -0.3421124 | BE68: -0.116927 | BF68: 0 | BG68: -0.04683 | BH68: -2.5 | BI68: 0 | BJ68: -0.105 | BK68: 0 | BL68: 0 | BM68: 0 | BN68: 0 | BO68: 0 | BP68: 0 | BQ68: 0 | BR68: 0 | BS68: 0 | BT68: 0 | BU68: 0 | BV68: 0 | BW68: 0 | BX68: 0 | BY68: 0 | BZ68: 0 | CA68: 0 | CB68: 0 | CC68: 0 | CD68: 0 | CE68: 0 | CF68: 0 | CG68: 0 | CH68: 0
B72: 1000000

Sheet LoV
B2: FY starts in: | C2: January
B4: Month | C4: Calendar year month number | D4: FY month number
B5: January | C5: 1 | D5: =IF(B5=$C$2,1,D16+1) -> 1
B6: February | C6: 2 | D6: =IF(B6=$C$2,1,D5+1) -> 2
B7: March | C7: 3 | D7: =IF(B7=$C$2,1,D6+1) -> 3
B8: April | C8: 4 | D8: =IF(B8=$C$2,1,D7+1) -> 4
B9: May | C9: 5 | D9: =IF(B9=$C$2,1,D8+1) -> 5
B10: June | C10: 6 | D10: =IF(B10=$C$2,1,D9+1) -> 6
B11: July | C11: 7 | D11: =IF(B11=$C$2,1,D10+1) -> 7
B12: August | C12: 8 | D12: =IF(B12=$C$2,1,D11+1) -> 8
B13: September | C13: 9 | D13: =IF(B13=$C$2,1,D12+1) -> 9
B14: October | C14: 10 | D14: =IF(B14=$C$2,1,D13+1) -> 10
B15: November | C15: 11 | D15: =IF(B15=$C$2,1,D14+1) -> 11
B16: December | C16: 12 | D16: =IF(B16=$C$2,1,D15+1) -> 12
